{
    "AdvancedSearch_Heading": "Cari di Pasar Komunitas",
    "AdvancedSearch_Reset": "Reset Filter",
    "AdvancedSearch_Search": "Cari",
    "AdvancedSearch_AppSelect_Placeholder": "Pilih game...",
    "AdvancedSearch_AppSelect_YourGames": "Game yang baru kamu mainkan dengan item",
    "AdvancedSearch_AppSelect_PopularGames": "Game populer dengan item",
    "AdvancedSearch_AppSelect_Clear": "Hapus pilihan",
    "AdvancedSearch_TextSearch_Placeholder": "Cari...",
    "AdvancedSearch_TextSearch_PlaceholderWithApp": "Cari di %1$s...",
    "AdvancedSearch_TypeSwitch_InGame": "Item dalam Game",
    "AdvancedSearch_TypeSwitch_SteamItems": "Item Steam",
    "AdvancedSearch_SteamItems_TypeLabel": "Jenis Item",
    "AdvancedSearch_NoFacets": "Game ini tidak memiliki filter Pasar.",
    "AdvancedSearch_NoFacetsSearch": "Klik \"Cari\" untuk melihat item yang tersedia.",
    "AdvancedSearch_FacetLoadError": "Terjadi kesalahan saat memuat filter untuk game ini.",
    "AdvancedSearch_PriceFieldLabel": "Harga",
    "AdvancedSearch_MinPricePlaceholder": "Terendah",
    "AdvancedSearch_MaxPricePlaceholder": "Tertinggi",
    "AdvancedSearch_CustomFilter_All": "Semua",
    "AdvancedSearch_CustomFilter_Other": "Lainnya",
    "AdvancedSearch_FilterGeneric_Placeholder": "Filter...",
    "AdvancedSearch_AppSelect_FilterPlaceholder": "Filter berdasarkan game...",
    "AdvancedSearch_BetaTag": "Fitur beta - Berikan masukan",
    "AdvancedSearch_TextSearch_Tooltip": "Cari nama item di seluruh Pasar...",
    "AdvancedSearch_Beta_OptOut": "Ganti ke filter lama",
    "AdvancedSearch_CSContainers_Tooltip": "Peti Senjata, Kapsul Stiker, Paket Suvenir, dll.",
    "Header_MarketTitle": "Pasar Komunitas Steam",
    "Header_MarketDescription": "Jual-beli item dengan anggota komunitas untuk menambahkan Saldo Steam Wallet",
    "Header_LearnMore": "Pelajari Lebih Lanjut",
    "Header_Search_Placeholder": "Cari di Pasar",
    "Header_Search_PlaceholderNew": "Pencarian baru...",
    "Header_Search_Filters": "Filter",
    "Header_OptOut": "Keluar dari Pasar Komunitas Steam Versi Beta",
    "CommodityExplanation": "Item ini adalah komoditas dan mewakili sekelompok item individual yang secara efektif identik. Tidak mungkin untuk mengiklankan setiap item secara individual. Namun, kamu dapat memesan sebanyak yang kamu inginkan dengan harga tertentu. Harga jual yang terendah akan selalu dicocokkan dengan penawaran pembelian tertinggi.",
    "Search_AmountFound": "%1$s hasil ditemukan",
    "Search_AmountFound_Plural": "%1$s hasil ditemukan",
    "Search_ListingsFound": "%2$s iklan penjualan ditemukan",
    "Search_ListingsFound_Plural": "%2$s iklan penjualan ditemukan",
    "SortBy_Default": "Popularitas (default)",
    "SortBy_Name_Asc": "Nama (A ke Z)",
    "SortBy_Name_Desc": "Nama (Z ke A)",
    "SortBy_Price_Asc": "Harga (rendah ke tinggi)",
    "SortBy_Price_Desc": "Harga (tinggi ke rendah)",
    "SortBy_Quantity_Asc": "Jumlah (rendah ke tinggi)",
    "SortBy_Quantity_Desc": "Jumlah (tinggi ke rendah)",
    "SortBy_AssetProperty_Asc": "%1$s (rendah ke tinggi)",
    "SortBy_AssetProperty_Desc": "%1$s (tinggi ke rendah)",
    "SortBy_Placeholder": "Urutkan Berdasarkan",
    "Search_Button": "Cari",
    "Search_Placeholder": "Cari...",
    "Button_Buy": "Beli",
    "Button_Sell": "Jual",
    "Button_BuyNow": "Beli Sekarang",
    "Button_BuyOrder": "Lakukan Penawaran Pembelian...",
    "BuyOrder_PlaceOrderHeader": "Lakukan penawaran pembelian:",
    "Button_Close": "Tutup",
    "Search_ListingQuantity": "Jumlah yang dijual: %1$s",
    "Bucket_PriceFrom": "Mulai %1$s",
    "AccessorySearch_AttachedAccessoryType": "%1$s Terpasang",
    "FilterResults_Placeholder": "Hasil Filter...",
    "AdvancedSearch_Header": "Pencarian Lanjutan",
    "AdvancedSearch_Link": "Pencarian Lanjutan",
    "MarketSearch_Placeholder": "Cari Item...",
    "Breadcrumbs_Home": "Beranda Pasar",
    "MarketHome_PopularApps": "Game Populer",
    "AdvancedSearch_IncludeDescriptions": "Masukkan deskripsi di pencarian",
    "AdvancedSearch_IncludeDescriptions_Tooltip": "Beberapa item lama menggunakan deskripsi tekstual untuk menyertakan properti penting yang tidak dapat diakses dengan filter di bawah ini. Opsi ini memungkinkan teks pencarian untuk mendapatkan teks deskripsi penuh, alih-alih hanya nama item.",
    "MarketSearch_FilterColumn_Header": "Filter",
    "MarketSearch_Reset": "Reset Pencarian",
    "Listings_TextFilter_Placeholder": "Masukkan teks filter kustom...",
    "Economy_Market_Purchase_Restrictions": "Setelah dibeli, item ini:",
    "Economy_Market_Purchase_TradableRestriction_1Day": "tidak dapat ditukarkan selama satu hari",
    "Economy_Market_Purchase_TradableRestriction_7Days": "tidak dapat ditukarkan selama satu minggu",
    "Economy_Market_Purchase_TradableRestriction_NDays": "tidak dapat ditukarkan selama %1$s hari",
    "Economy_Market_Purchase_TradableRestriction_Permanent": "tidak dapat ditukarkan",
    "Economy_Market_Purchase_MarketableRestriction_1Day": "tidak dapat dijual di Pasar Komunitas Steam selama satu hari",
    "Economy_Market_Purchase_MarketableRestriction_7Days": "tidak dapat dijual di Pasar Komunitas Steam selama satu minggu",
    "Economy_Market_Purchase_MarketableRestriction_NDays": "tidak dapat dijual di Pasar Komunitas Steam selama %1$s hari",
    "Economy_Market_Purchase_MarketableRestriction_None": "bisa langsung dijual lagi di Pasar Komunitas Steam",
    "PurchaseDialog_Header": "Beli item",
    "PurchaseDialog_Details_Column_Name": "Nama",
    "PurchaseDialog_Details_Column_Price": "Harga",
    "PurchaseDialog_Subtotal_Label": "Subtotal:",
    "PurchaseDialog_PublisherFee_Label": "Biaya %1$s (%2$s%):",
    "PurchaseDialog_PublisherFee_Label_Generic": "Biaya game (%1$s%):",
    "PurchaseDialog_SteamFee_Label": "Biaya transaksi Steam (%1$s%):",
    "PurchaseDialog_LocalTax_Label": "Pajak penjualan lokal (%1$s):",
    "PurchaseDialog_Total_Label": "Total:",
    "PurchaseDialog_PaymentMethod_Label": "Metode pembayaran:",
    "PurchaseDialog_PaymentMethod_Wallet": "Steam Wallet",
    "PurchaseDialog_SteamAccount_Label": "Akun Steam:",
    "PurchaseDialog_BillingInfo_Label": "Alamat penagihan:",
    "PurchaseDialog_BillingInfo_FirstName": "Nama depan",
    "PurchaseDialog_BillingInfo_LastName": "Nama belakang",
    "PurchaseDialog_BillingInfo_Address": "Alamat penagihan",
    "PurchaseDialog_BillingInfo_AddressLine2": "Baris 2 alamat penagihan",
    "PurchaseDialog_BillingInfo_City": "Kota",
    "PurchaseDialog_BillingInfo_StateProvince": "Negara Bagian/Provinsi",
    "PurchaseDialog_BillingInfo_ZipPostal": "Kode pos",
    "PurchaseDialog_BillingInfo_Country": "Negara",
    "PurchaseDialog_BillingInfo_SaveInfo": "Simpan alamat saya untuk pembelian yang lebih mudah selanjutnya",
    "PurchaseDialog_Action_AddFunds": "Tambahkan Dana",
    "PurchaseDialog_Action_Purchase": "Beli",
    "PurchaseDialog_SSA_Link": "Saya setuju dengan ketentuan %1$s (terakhir diperbarui %2$s)",
    "PurchaseDialog_SSA_Link_Title": "Perjanjian Pelanggan Steam",
    "PurchaseDialog_SSA_Fail": "Kamu harus menyetujui Perjanjian Pelanggan Steam untuk menyelesaikan transaksi ini.",
    "PurchaseDialog_EU_SSA": "Dengan mengeklik \"Beli\", kamu akan langsung menerima akses ke konten digital ini, dan setuju bahwa pembelian ini bersifat final dan tidak dapat dibatalkan.",
    "PurchaseDialog_Error_ServerGeneric": "Terjadi kendala saat membeli item ini. Kemungkinan iklan penjualannya sudah dihapus. Refresh halamannya dan coba lagi.",
    "PurchaseDialog_Error_NoConfirmation": "Terjadi kendala saat membeli item. Terjadi kesalahan saat menunggumu mengonfirmasikan tindakan ini. Refresh halaman dan coba lagi.",
    "PurchaseDialog_Error_MissingRequired": "Kolom-kolom berikut ini wajib diisi:",
    "PurchaseDialog_Error_InvalidMilitaryCity": "Mohon masukkan alamat militer yang valid",
    "PurchaseDialog_Error_InvalidPostal": "Silakan masukkan kode pos yang valid",
    "PurchaseDialog_PurchaseComplete": "Selamat atas pembelianmu! Kamu bisa melihat item baru tersebut di <1>invetarismu</1>.",
    "PurchaseDialog_Button_ViewInventory": "Lihat Inventaris",
    "PurchaseDialog_Confirmation_Title": "Konfirmasi tambahan diperlukan",
    "PurchaseDialog_Confirmation_Title_Wait": "Kami menunggumu untuk mengonfirmasikan pembelian ini...",
    "PurchaseDialog_Confirmation_Body_Mobile": "Beberapa pembelian membutuhkan keamanan ekstra via aplikasi Seluler Steam.",
    "PurchaseDialog_Confirmation_Body_Email": "Beberapa pembelian membutuhkan keamanan ekstra via email Steam Guard.",
    "PurchaseDialog_Confirmation_Body_Unknown": "Beberapa pembelian membutuhkan keamanan ekstra via aplikasi Seluler Steam atau email.",
    "PurchaseDialog_Confirmation_Description_Mobile": "Konfirmasikan via Aplikasi Seluler Steam untuk menyelesaikan pembelianmu...",
    "PurchaseDialog_Confirmation_Description_Email": "Konfirmasikan via email untuk menyelesaikan pembelianmu...",
    "PurchaseDialog_Confirmation_Description_Unknown": "Konfirmasikan via Aplikasi Seluler Steam atau email untuk menyelesaikan pembelianmu...",
    "PurchaseDialog_Purchase_Successful": "Pembelian berhasil dilakukan",
    "PurchaseDialog_Close": "Tutup",
    "PurchaseDialog_ViewInventory": "Lihat Inventaris",
    "PurhcaseDialog_SaveMyAddress": "Simpan alamat saya untuk pembelian yang lebih cepat selanjutnya",
    "Listing_NotAvailable": "Iklan Penjualan ini sudah tidak tersedia lagi",
    "Listing_NotAvailable_Short": "Tidak Tersedia",
    "Listing_NotAvailable_Long": "Iklan Penjualan ini tidak lagi tersedia untuk pembelian.",
    "BuyOrderDialog_Header": "Beli - %1$s",
    "BuyOrderDialog_Header_NoItem": "Lakukan Penawaran Pembelian",
    "BuyOrderDialog_BucketPicker_Label": "Jenis item apa yang ingin kamu beli?",
    "BuyOrderDialog_BucketPicker_Placeholder": "Pilih item...",
    "BuyOrderDialog_PriceField": "Harga yang ingin kamu bayar:",
    "BuyOrderDialog_PriceField_Suffix": "(tiap item)",
    "BuyOrderDialog_QuantityField": "Jumlah barang yang ingin dibeli:",
    "BuyOrderDialog_MaxPrice": "Harga tertinggi %1$s:",
    "BuyOrderDialog_MaxPrice_Tip": "Ini adalah harga tertinggi yang akan kamu bayar untuk penawaran pembelian ini. Item tersebut akan dibeli dengan harga yang terendah, jadi jumlah yang akan kamu bayar bisa kurang dari harga ini.",
    "BuyOrderDialog_Status_Pending": "Mencari iklan penjualan item dengan harga yang kamu inginkan...",
    "BuyOrderDialog_Status_Filled": "Berhasil! Sekarang item-nya sudah di dalam inventarismu dan bukti pembayaran sudah dikirim ke email-mu.",
    "BuyOrderDialog_Status_Settled": "Berhasil! Penawaran pembelian telah dilakukan.",
    "BuyOrderDialog_Status_Settled_Note": "Kamu akan diberi tahu secara otomatis via email saat pembelian selesai. Batalkan penawaran pembelian ini di bagian atas halaman ini atau dari halaman beranda pasar, jika diinginkan.",
    "BuyOrderDialog_Status_GenericError": "Maaf! Server Steam mengalami kendala dalam memproses pesananmu. Silakan periksa ulang apakah pesananmu sudah dibuat atau belum. Jika belum, silakan coba lagi nanti.",
    "BuyOrderDialog_MinPriceError": "Harga minimum per unit adalah %1$s",
    "OrderBook_Table_PriceOrLess": "%1$s atau kurang",
    "OrderBook_Table_PriceOrMore": "%1$s atau lebih",
    "OrderBook_Table_Price": "Harga",
    "OrderBook_Table_Quantity": "Jumlah",
    "OrderBook_SellOrder_Description": "%1$s dijual dimulai dari %2$s",
    "OrderBook_SellOrder_Description_None": "Tidak ada iklan penjualan yang aktif untuk item ini",
    "OrderBook_BuyOrder_Description": "%1$s ingin membeli dengan harga %2$s atau kurang",
    "OrderBook_BuyOrder_Description_None": "Tidak ada penawaran pembelian yang sedang aktif.",
    "OrderBook_BuyOrder_NeedBucket": "Pilih item tertentu untuk melihat informasi penawaran pembelian",
    "OrderBook_Graph_Title": "Penawaran Pembelian dan Penjualan (kumulatif)",
    "OrderBook_Graph_BuyTooltip": "1 penawaran pembelian seharga %2$s atau lebih tinggi",
    "OrderBook_Graph_BuyTooltip_Plural": "%1$s penawaran pembelian seharga %2$s atau lebih tinggi",
    "OrderBook_Graph_SellTooltip": "1 penawaran penjualan seharga %2$s atau lebih tinggi",
    "OrderBook_Graph_SellTooltip_Plural": "%1$s penawaran penjualan seharga %2$s atau lebih tinggi",
    "OrderBook_PlaceOrder_BuyRequests": "1 permintaan untuk membeli dengan harga <1>%2$s</1>",
    "OrderBook_PlaceOrder_BuyRequests_Plural": "%3$s ingin membeli dengan harga <1>%2$s atau lebih rendah</1>",
    "MedianSalePrice_Graph_Title": "Median Harga Penjualan",
    "Graph_TimeScale_Week": "Minggu",
    "Graph_TimeScale_Month": "Bulan",
    "Graph_TimeScale_Year": "Tahun",
    "Graph_TimeScale_Lifetime": "Sepanjang Waktu",
    "Graph_NumberSold": "%1$s terjual",
    "Graph_Label_Price": "Harga",
    "Graph_Label_Volume": "Volume",
    "Graph_NoData": "Tidak ada data untuk rentang waktu ini",
    "Graph_Tooltip_NoPurchaseData": "Tidak ada data pembelian",
    "Graph_Tooltip_NA": "N/A",
    "MyOrders_GridHeader_Name": "NAMA",
    "MyOrders_GridHeader_Price": "HARGA",
    "MyOrders_GridHeader_Quantity": "JUMLAH",
    "MyOrders_GridHeader_DateListed": "DIIKLANKAN",
    "MyOrders_Cancel": "Batal",
    "MyOrders_Remove": "Hapus",
    "MyOrders_Heading": "Penawaran Aktif Saya",
    "MyOrders_Heading_Sell": "Penawaran Penjualan",
    "MyOrders_Heading_Buy": "Penawaran Pembelian",
    "MyOrders_Heading_MyPurchaseOffers": "Pembelian - Penawaran Saya",
    "MyOrders_Heading_MyListings": "Penjualan - Iklan Penjualan Saya",
    "MyOrders_FailedToLoad": "Terjadi kendala saat memuat data penawaran untuk item ini.",
    "MyOrders_NoActiveOrders_Item": "Tidak ada penawaran aktif untuk item ini.",
    "MyOrders_NoBuyOrders_Item": "Tidak ada penawaran pembelian aktif untuk item ini.",
    "MyOrders_NoSellOrders_Item": "Kamu belum menjual item-item ini. Jual item dari inventarismu atau klik tombol \"Jual\" di halaman ini.",
    "CancelBuyOrder_GenericError": "Terjadi kendala saat membatalkan penawaran. Silakan coba lagi nanti.",
    "CancelListing_GenericError": "Terjadi kendala saat menghapus Iklan Penjualan. Silakan coba lagi nanti.",
    "CancelListing_Dialog_Header": "Hapus iklan penjualan",
    "CancelListing_Dialog_Prompt": "Apakah kamu ingin menghapus iklan penjualan %1$s dan mengembalikan item-nya ke inventarismu?",
    "CancelListing_Dialog_Prompt_Generic": "Apakah kamu ingin menghapus iklan penjualan ini dan mengembalikan item-nya ke inventarismu?",
    "CancelListing_Dialog_Yes": "Ya, hapus iklan penjualan ini",
    "CancelListing_Dialog_No": "Tidak",
    "CancelListing_Dialog_Success": "Iklan Penjualan berhasil dihapus",
    "SellDialog_Frame_Title": "Pilih item dari inventarismu",
    "UniqueBuyOrder_Explanation_Header": "Apa itu penawaran pembelian?",
    "UniqueBuyOrder_Explanation_1": "Tetapkan harga pilihanmu dan pembelian akan dilakukan secara otomatis ketika item tersedia dengan harga tersebut.",
    "UniqueBuyOrder_Explanation_2": "Steam akan memastikan kamu mendapatkan harga terbaik yang tersedia.",
    "UniqueBuyOrder_Explanation_3": "Untuk item ini, penawaran pembelian akan dicocokkan dengan item dengan harga terendah tanpa mempertimbangkan karakteristik uniknya.",
    "Error_Sorry": "Maaf!",
    "Error_Encountered": "Terjadi kesalahan saat memproses permintaanmu:",
    "Error_TooManyRequests_Description": "Kamu terlalu banyak mengajukan permintaan baru-baru ini. Mohon tunggu dan coba lagi nanti.",
    "Container_ContentsLabel": "Kemungkinan Isi:",
    "Error_LoadingContent": "Terjadi kendala saat memuat konten ini",
    "Error_LoadingMarketItem": "Item yang diminta mungkin tidak ada, atau terjadi masalah sementara yang mencegah item ini dimuat. Silakan coba lagi nanti.",
    "ListingFilter_Title": "Filter Iklan Penjualan",
    "Listings_NoneFound": "Tidak Menemukan Iklan Penjualan",
    "Mobile_InfoSection": "Info",
    "Mobile_GraphSection": "Grafik penjualan",
    "Mobile_BuyOrderSection": "Penawaran Pembelian",
    "Mobile_FiltersButton": "Filter",
    "AssetProperty_Range_MinPlaceholder": "Min.",
    "AssetProperty_Range_MaxPlaceholder": "Maks.",
    "Accessories_FieldSectionLabel": "Aksesori",
    "AccessoriesList_Title": "Aksesori",
    "Item_CountryBuySellRestricted": "Kamu tidak dapat membeli item ini karena jual beli item ini tidak bisa dilakukan di negaramu.",
    "Item_CountryBuyRestricted": "Kamu tidak dapat membeli item ini karena pembelian item ini tidak bisa dilakukan di negaramu.",
    "Listing_EnhancedAppearance_Missing": "Iklan Penjualan ini belum memiliki gambar unik atau yang disempurnakan. Gambar yang ditampilkan di sini mungkin sedikit berbeda dengan item yang diiklankan.",
    "Listing_EnhancedAppearance_ShowBackground": "Tampilkan latar",
    "Listing_SomethingWentWrong": "Terjadi kesalahan saat mencoba menampilkan iklan penjualan ini",
    "Unavailable_Header": "Kamu tidak dapat melakukan jual beli di Pasar Komunitas Steam karena alasan berikut:",
    "Unavailable_Header_Plural": "Kamu tidak dapat melakukan jual beli di Pasar Komunitas Steam karena alasan berikut:",
    "Economy_Market_TopLevelReason_AccountLocked": "Saat ini akunmu sedang dikunci.",
    "Economy_Market_TopLevelTooltip_AccountLocked": "Informasi terkait penguncian ini dapat dilihat dengan mengeklik tombol bar merah yang terlihat di bagian pojok kanan atas saat masuk ke Steam client. Silakan hubungi Bantuan Steam untuk info lebih lanjut.",
    "Economy_Market_HeaderTip_AccountLocked": "Saat ini akunmu terkunci. Informasi terkait penguncian ini dapat dilihat dengan mengeklik tombol bar merah yang terlihat di bagian pojok kanan atas saat masuk ke Steam client.",
    "Economy_Market_TopLevelTooltip_RemoveRestrictionLink": "Untuk mencabut pembatasan ini...",
    "Economy_Market_TopLevelReason_AccountTradeBanned": "Saat ini akunmu sedang dalam masa ban pertukaran.",
    "Economy_Market_TopLevelTooltip_AccountTradeBanned": "Durasi ban pertukaran bisa berlaku untuk sementara waktu sampai permanen. Silakan klik tombol bar merah yang terlihat di bagian pojok kanan atas saat masuk ke Steam client untuk melihat durasi waktu ban pertukaran tersebut.",
    "Economy_Market_HeaderTip_AccountTradeBanned": "Akunmu di-ban dari melakukan pertukaran. Silakan klik tombol bar merah yang terlihat di bagian pojok kanan atas saat masuk ke Steam client untuk melihat durasi waktu ban pertukaran tersebut.",
    "Economy_Market_TopLevelTooltip_MoreInfoLink": "Info lebih lanjut...",
    "Economy_Market_TopLevelReason_AccountNotTrusted": "Kamu harus melakukan pembelian yang valid di Steam dalam kurun waktu %1$s hari sampai 1 tahun tanpa adanya kasus tolak bayar atau sengketa pembayaran.",
    "Economy_Market_TopLevelTooltip_AccountNotTrusted": "Silakan lakukan pembelian di Toko Steam berupa dana wallet, game, dan DLC. Namun, CD key dan hadiah bukanlah pembelian yang valid. Bantuan Steam tidak dapat mencabut pembatasan ini.",
    "Economy_Market_HeaderTip_AccountNotTrusted": "Kamu sudah harus melakukan pembelian di Steam dalam kurun waktu %1$s hari sampai satu tahun tanpa adanya kasus tolak bayar atau sengketa pembayaran. Bantuan Steam tidak dapat menghapus pembatasan ini.",
    "Economy_Market_TopLevelReason_AccountNotTrusted_Waiting": "Kelihatannya, kamu telah melakukan pembelian yang valid di Toko Steam, tapi belum lebih dari %1$s hari.",
    "Economy_Market_TTopLevelTooltip_AccountNotTrusted_Waiting": "Kami memerlukan bukti pembelian di Steam dalam kurun waktu %1$s hari sampai 1 tahun tanpa adanya kasus tolak bayar atau sengketa pembayaran. Kamu baru saja melakukan pembelian, tapi belum lebih dari %1$s hari. Bantuan Steam tidak dapat mencabut pembatasan ini.",
    "Economy_Market_TopLevelReason_AccountPasswordRecentlyReset": "Kata sandi akunmu baru saja direset.",
    "Economy_Market_TopLevelTooltip_AccountPasswordRecentlyReset": "Pembatasan ini akan dicabut dalam %1$s hari secara otomatis setelah kata sandi akun tersebut direset. Jika akunnya belum digunakan dalam waktu yang lama, pembatasan ini bisa berlaku sampai dengan %2$s hari. Pembatasan ini hanya berlaku untuk proses mereset kata sandi. Mengubah kata sandi akun tidak akan memberlakukan pembatasan apa pun. Bantuan Steam tidak dapat mencabut pembatasan apa pun.",
    "Economy_Market_HeaderTip_AccountPasswordRecentlyReset": "Kamu baru saja mereset kata sandi untuk akun Steam-mu. Untuk melindungi pengguna yang akun email-nya ataupun akun lainnya telah disusupi, kami membatasi akses ke Pasar Komunitas selama %1$s hari setelah kata sandi direset.",
    "Economy_Market_HeaderTip_NewPaymentMethod_NoDate": "Kamu baru saja mengisi dana Steam Wallet-mu menggunakan kartu kredit yang belum terverifikasi dan sering digunakan akhir-akhir ini. Kamu dapat mencoba <1>memverifikasikan dana sekarang</1> atau menunggu sampai pembatasan dihapus secara otomatis.\n\nCATATAN: Proses verifikasi dana mungkin tidak berfungsi dengan semua bank atau kartu kredit. Jika kamu tidak dapat memverifikasikan kartumu, maka kamu harus menunggu sampai metode pembayaran diverifikasikan dengan Steam. Bantuan Steam tidak dapat memberikan atau mengubah verifikasi tagihan dan tidak dapat menghapus pembatasan ini.",
    "Economy_Market_HeaderTip_AccountHasNewPaymentMethod": "Kamu baru saja mengisi dana Steam Wallet-mu melalui PayPal atau metode pembayaran yang belum diverifikasi dan sering digunakan akhir-akhir ini. Kamu tidak dapat mengakses Pasar selama beberapa hari saat dananya diverifikasi.",
    "Economy_Market_TopLevelReason_AccountHasNewPaymentMethod": "Kamu baru saja mengisi dana Steam Wallet-mu melalui akun Paypal baru atau metode pembayaran yang belum diverifikasi dan sering digunakan akhir-akhir ini. Kamu tidak dapat mengakses Pasar selama beberapa hari saat dananya diverifikasi terlebih dahulu.",
    "Economy_Market_TopLevelReason_AcceptedWalletGift": "Kamu baru saja menerima kartu hadiah digital dari temanmu.",
    "Economy_Market_HeaderTip_AcceptedWalletGift": "Kamu baru saja menerima sebuah kartu hadiah digital dari teman. Kamu tidak akan bisa mengakses Pasar Komunitas Steam selama %1$s hari setelah temanmu membeli kartu hadiah tersebut.",
    "Economy_Market_TopLevelReason_InvalidCookie": "Steam mengalami kendala saat memakai cookie perambanmu.",
    "Economy_Market_TopLevelTooltip_InvalidCookie": "Cookie perambanmu tidak valid. Silakan coba keluar dan login kembali ke Steam. Pastikan juga bahwa cookie perambanmu sudah diaktifkan dengan benar dan tidak ada tambahan peramban yang berbentrokan dengan cookie Steam.",
    "Economy_Market_HeaderTip_InvalidCookie": "Kemungkinan perambanmu tidak mengaktifkan Cookie. Pastikan semua cookie diizinkan di perambanmu. Silakan keluar dan login ulang ke Steam.",
    "Economy_Market_TopLevelReason_NewDevice": "Kamu masuk ke Pasar dari perangkat yang belum dilindungi oleh Steam Guard selama %1$s hari.",
    "Economy_Market_TopLevelTooltip_NewDevice": "Jika kamu memiliki perangkat yang sudah diverifikasi, kamu masih bisa mengakses Pasar melalui perangkat tersebut. Jika tidak, kamu harus menunggu perangkat ini diverifikasi terlebih dahulu sebelum dapat mengakses Pasar.",
    "Economy_Market_HeaderTip_NewDevice": "Kamu baru saja login di perangkat atau peramban baru. Agar item di inventarismu terlindungi, kamu tidak akan bisa mengakses pasar dari perangkat ini selama %1$s hari.",
    "Economy_Market_TopLevelReason_SelfRefund": "Kamu baru saja mengembalikan dana sebuah transaksi ke dalam Steam Wallet-mu.",
    "Economy_Market_TopLevelTooltip_SelfRefund": "Kamu tidak dapat mengakses Pasar selama %1$s hari setelah danamu baru saja dikembalikan. Bantuan Steam tidak dapat mencabut pembatasan apa pun.",
    "Economy_Market_HeaderTip_SelfRefund": "Kamu baru saja mengembalikan dana sebuah transaksi ke dalam Steam Wallet-mu. Kamu tidak akan bisa mengakses Pasar selama %1$s hari setelah danamu dikembalikan.",
    "Economy_Market_TopLevelReason_LimitedUser": "Akunmu dibatasi.",
    "Economy_Market_TopLevelTooltip_LimitedUser": "Akunmu dibatasi dan tidak memiliki akses ke beberapa fitur Steam seperti Pasar Komunitas Steam.",
    "Economy_Market_HeaderTip_LimitedUser": "Akunmu dibatasi dan tidak memiliki akses ke beberapa fitur Steam seperti Pasar Komunitas Steam.",
    "Economy_Market_HeaderTip_SteamGuardOnlyRecentlyEnabled": "Kamu baru saja mereset atau mengaktifkan Steam Guard. Kamu harus menunggu selama %1$s hari setelah Steam Guard diaktifkan.",
    "Economy_Market_TopLevelTooltip_SteamGuardRecentlyEnabled": "Kamu harus menunggu sampai Steam Guard telah diaktifkan di akunmu selama 15 hari. Bantuan Steam tidak dapat mencabut pembatasan ini.",
    "Economy_Market_TopLevelReason_NoSteamGuard": "Akunmu harus dilindungi oleh Steam Guard setidaknya selama %1$s hari.",
    "Economy_Market_TopLevelTooltip_SteamGuardDisabled": "Kamu harus mengaktifkan Steam Guard di dalam akunmu. Pastikan bahwa email-mu sudah diverifikasi dan kamu login setidaknya dua kali ke akunmu setelah mengaktifkan Steam Guard.",
    "Economy_Market_HeaderTip_NoSteamGuard": "Akunmu harus dilindungi oleh Steam Guard setidaknya selama %1$s hari."
}
