{
    "language": "greek",
    "LoginRedirect_Dialog_Title": "Σύνδεση",
    "LoginRedirect_Dialog_Description": "Συνδεθείτε για να προσθέσετε αυτό το αντικείμενο στη Λίστα Επιθυμιών σας, να το ακολουθήσετε ή να το αγνοήσετε. Με κλικ στο ΟΚ θα ανακατευθυνθείτε στη σελίδα σύνδεσης.",
    "Wishlist_NotSignedIn": "Συνδεθείτε ή ανοίξτε αυτήν τη σελίδα στην εφαρμογή Steam για προσθήκη στη Λίστα Επιθυμιών, ακολούθηση ή αγορά.",
    "VerifiedProgram_DeckTitle": "Το %1$s είναι %2$s στο Steam Deck",
    "VerifiedProgram_DeckTitle_Verified": "Επαληθευμένο",
    "VerifiedProgram_DeckSubTitle": "Αυτό το παιχνίδι και πολλά ακόμα έχουν ελεγχθεί πλήρως και λειτουργούν %1$s.",
    "VerifiedProgram_GreatOnDeck": "Υπέροχα στο Steam Deck",
    "VerifiedProgram_DeckAlt": "Εικονίδιο επαλήθευσης",
    "VerifiedProgram_DeckDeviceAlt": "Steam Deck OLED",
    "VerifiedProgram_DeckShopBannerAlt": "Μπάνερ Steam Deck: «Τα παιχνίδια σας, παντού»",
    "VerifiedProgram_DeckDisclaimer": "Το τρέιλερ ενδέχεται να μην είναι αντιπροσωπευτικό της πραγματικής εμπειρίας παιχνιδιού στο Steam Deck",
    "StoreItemFound": "%1$s Βρέθηκαν (%2$s)",
    "StoreItemNotFound": "Δεν βρέθηκε (%1$s)",
    "SteamURLAccepted": "Το URL είναι αποδεκτό: %1$s",
    "SteamURLInvalid": "Σφάλμα: Το URL δεν αντιστοιχεί σε ιδιοκτησία του Steam (Κατάστημα/Κοινότητα)",
    "AnchorHashInputInvalid": "Invalid Input",
    "Reservation_JoinPool": "Join the List",
    "Reserationn_NoListJoined": "Επιλέξτε έως και %1$s από τα παρακάτω μοντέλα για να μπείτε στη λίστα.",
    "Reservation_InPool": "Μπήκατε στη λίστα για τα επιλεγμένα μοντέλα παρακάτω %2$s",
    "Reservation_InPool_NoDate": "You are on the list for the selected models below",
    "Reservation_Cancel_Pool": "Leave the list?",
    "Reservation_Cancel_Pool_Desc": "By leaving you will not be included in the randomized list for this model. Are you sure?",
    "Reservation_JoinPool_Terms": "I've read and accept the <1>Terms and Conditions</1>.",
    "Reservation_JoinPool_ClickTerms": "Ελέγξτε τους όρους και τις προϋποθέσεις παρακάτω.",
    "Reservation_Pool_NotSignedIn": "Sign in to join the list",
    "Reservation_Pool_NotSignedIn_Desc": "Συνδεθείτε στο Steam για να μπείτε στη λίστα. Επιλέξτε ΟΚ για να μεταβείτε στη σελίδα σύνδεσης.",
    "Reservation_InPool_Message": "Μπείτε στη λίστα οποιαδήποτε στιγμή πριν από τις 25 Ιουνίου, στις 8 μ.μ. ώρα Ελλάδας. Εκείνη την ημέρα, η λίστα θα κλείσει και θα γίνει τυχαία κατανομή. Σύντομα μετά την ολοκλήρωση της διαδικασίας, θα λάβετε ένα email με τα αποτελέσματά σας.",
    "Reservation_JoinWaitList": "Join the Waitlist",
    "Reservation_Cancel_Waitlist": "Leave the Waitlist?",
    "Reservation_Cancel_Waitlist_Desc": "Εάν αποχωρήσετε από τη λίστα αναμονής, χάνετε τη θέση σας. Εάν κάνετε επανεγγραφή, θα μπείτε στο τέλος της λίστας.",
    "Reservation_Change_WaitList": "Αλλαγή λίστας αναμονής;",
    "Reservation_Change_WaitList_Desc1": "Εάν αλλάξετε λίστα αναμονής, θα αποχωρήσετε από τη λίστα αναμονής για το %1$s και θα χάσετε τη θέση σας στη σειρά.",
    "Reservation_Change_WaitList_Desc2": "You are joining the waitlist for %1$s.",
    "Reservation_In_Waitlist": "On waitlist since %2$s",
    "Reservation_In_Waitlist_WithName": "Στη λίστα αναμονής για %1$s από %2$s",
    "Reservation_In_Waitlist_NoDate": "On waitlist",
    "Reservation_In_Waitlist_WithName_NoDate": "You are on the waitlist for %1$s",
    "Reservation_In_Waitlist_Message": "We will email you if a unit becomes available.",
    "Reservation_In_Waitlist_Message_NotJoin": "Join the waitlist, and you will be notified if units become available.",
    "Reservation_Waitlist_NotSignedIn": "Sign in to join the waitlist",
    "Reservation_Waitlist_NotSignedIn_Desc": "Sign in to Steam to join the waitlist. Select OK to go to the sign in page.",
    "Reservation_OnRegularReserveForModel": "You are in the reservation queue for %1$s",
    "Reservation_PostShuffle_TAndC": "<1>Terms and Conditions</1> apply.",
    "machine_dummy": "dummy",
    "PriceGrid_NormalPrice": "ΚΑΝΟΝΙΚΗ",
    "PriceGrid_RecentPrice": "ΧΑΜΗΛΟΤΕΡΗ (30 ΗΜΕΡΕΣ)",
    "PriceGrid_CurrentPrice": "ΤΩΡΑ",
    "Dummy": "dummy"
}
