{
    "AdvancedSearch_Heading": "Buscar no Mercado da Comunidade",
    "AdvancedSearch_Reset": "Redefinir filtros",
    "AdvancedSearch_Search": "Buscar",
    "AdvancedSearch_AppSelect_Placeholder": "Selecione um jogo...",
    "AdvancedSearch_AppSelect_YourGames": "Recém-jogados com itens",
    "AdvancedSearch_AppSelect_PopularGames": "Jogos populares com itens",
    "AdvancedSearch_AppSelect_Clear": "Limpar seleção",
    "AdvancedSearch_TextSearch_Placeholder": "Buscar...",
    "AdvancedSearch_TextSearch_PlaceholderWithApp": "Buscar em %1$s...",
    "AdvancedSearch_TypeSwitch_InGame": "Itens do jogo",
    "AdvancedSearch_TypeSwitch_SteamItems": "Itens do Steam",
    "AdvancedSearch_SteamItems_TypeLabel": "Tipo do item",
    "AdvancedSearch_NoFacets": "Este jogo não tem filtros de Mercado.",
    "AdvancedSearch_NoFacetsSearch": "Clique em \"Buscar\" para ver os itens disponíveis.",
    "AdvancedSearch_FacetLoadError": "Houve um erro ao carregar os filtros para este jogo.",
    "AdvancedSearch_PriceFieldLabel": "Preço",
    "AdvancedSearch_MinPricePlaceholder": "Preço mín.",
    "AdvancedSearch_MaxPricePlaceholder": "Preço máx.",
    "AdvancedSearch_CustomFilter_All": "Tudo",
    "AdvancedSearch_CustomFilter_Other": "Outro",
    "AdvancedSearch_FilterGeneric_Placeholder": "Filtrar...",
    "AdvancedSearch_AppSelect_FilterPlaceholder": "Filtrar por jogo...",
    "AdvancedSearch_BetaTag": "Recurso beta — compartilhe comentários",
    "AdvancedSearch_TextSearch_Tooltip": "Buscar nomes de itens no Mercado...",
    "AdvancedSearch_Beta_OptOut": "Alternar para filtros antigos",
    "AdvancedSearch_CSContainers_Tooltip": "Caixas de Armas, Cápsulas de Adesivos, Pacotes de Lembrança etc.",
    "Header_MarketTitle": "Mercado da Comunidade Steam",
    "Header_MarketDescription": "Compre e venda itens para membros da comunidade com o saldo da Carteira Steam",
    "Header_LearnMore": "Saiba mais",
    "Header_Search_Placeholder": "Buscar no Mercado",
    "Header_Search_Filters": "Filtros",
    "CommodityExplanation": "Este item é uma commodity, onde todos os itens individuais são efetivamente idênticos. Não é possível acessar anúncios individuais; no entanto, você pode fazer uma encomenda para comprar a um preço especifico, sendo que o anúncio mais barato será automaticamente associado à encomenda de maior quantidade.",
    "Search_AmountFound": "%1$s resultado",
    "Search_AmountFound_Plural": "%1$s resultados encontrados",
    "Search_ListingsFound": "%2$s anúncio encontrado",
    "Search_ListingsFound_Plural": "%2$s anúncios encontrados",
    "SortBy_Default": "Popularidade (padrão)",
    "SortBy_Name_Asc": "Nome (A a Z)",
    "SortBy_Name_Desc": "Nome (Z a A)",
    "SortBy_Price_Asc": "Preço (crescente)",
    "SortBy_Price_Desc": "Preço (decrescente)",
    "SortBy_Quantity_Asc": "Quantidade (crescente)",
    "SortBy_Quantity_Desc": "Quantidade (decrescente)",
    "SortBy_AssetProperty_Asc": "%1$s (crescente)",
    "SortBy_AssetProperty_Desc": "%1$s (decrescente)",
    "SortBy_Placeholder": "Ordenar",
    "Search_Button": "Buscar",
    "Search_Placeholder": "Buscar...",
    "Button_Buy": "Comprar",
    "Button_Sell": "Vender",
    "Button_BuyNow": "Comprar agora",
    "Button_BuyOrder": "Encomendar...",
    "BuyOrder_PlaceOrderHeader": "Encomendar:",
    "Button_Close": "Fechar",
    "Search_ListingQuantity": "Quantidade à venda: %1$s",
    "Bucket_PriceFrom": "A partir de %1$s",
    "AccessorySearch_AttachedAccessoryType": "%1$s",
    "FilterResults_Placeholder": "Filtrar resultados...",
    "AdvancedSearch_Header": "Busca avançada",
    "AdvancedSearch_Link": "Busca avançada",
    "MarketSearch_Placeholder": "Buscar um item...",
    "Breadcrumbs_Home": "Página inicial do Mercado",
    "MarketHome_PopularApps": "Jogos populares",
    "AdvancedSearch_IncludeDescriptions": "Incluir descrições na busca",
    "AdvancedSearch_IncludeDescriptions_Tooltip": "Algumas entradas mais antigas usam descrições textuais para propriedades importantes que não são acessíveis com os filtros abaixo. Esta opção permitirá que o texto buscado seja comparado com a descrição completa em vez de apenas com o nome da entrada.",
    "MarketSearch_FilterColumn_Header": "Filtros",
    "MarketSearch_Reset": "Redefinir busca",
    "Listings_TextFilter_Placeholder": "Inserir texto de filtro personalizado...",
    "Economy_Market_Purchase_Restrictions": "Após a compra, este item:",
    "Economy_Market_Purchase_TradableRestriction_1Day": "não será trocável por um dia",
    "Economy_Market_Purchase_TradableRestriction_7Days": "não será trocável por uma semana",
    "Economy_Market_Purchase_TradableRestriction_NDays": "não será trocável por %1$s dias",
    "Economy_Market_Purchase_TradableRestriction_Permanent": "não será trocável",
    "Economy_Market_Purchase_MarketableRestriction_1Day": "não poderá ser anunciado no Mercado da Comunidade por um dia",
    "Economy_Market_Purchase_MarketableRestriction_7Days": "não poderá ser anunciado no Mercado da Comunidade por uma semana",
    "Economy_Market_Purchase_MarketableRestriction_NDays": "não poderá ser anunciado no Mercado da Comunidade por %1$s dias",
    "Economy_Market_Purchase_MarketableRestriction_None": "poderá ser revendido no Mercado da Comunidade Steam imediatamente",
    "PurchaseDialog_Header": "Comprar um item",
    "PurchaseDialog_Details_Column_Name": "Nome",
    "PurchaseDialog_Details_Column_Price": "Preço",
    "PurchaseDialog_Subtotal_Label": "Subtotal:",
    "PurchaseDialog_PublisherFee_Label": "Tarifa de %1$s (%2$s%):",
    "PurchaseDialog_PublisherFee_Label_Generic": "Tarifa do jogo (%1$s%):",
    "PurchaseDialog_SteamFee_Label": "Tarifa de transação do Steam (%1$s%):",
    "PurchaseDialog_LocalTax_Label": "Imposto local sobre vendas (%1$s):",
    "PurchaseDialog_Total_Label": "Total:",
    "PurchaseDialog_PaymentMethod_Label": "Forma de pagamento:",
    "PurchaseDialog_PaymentMethod_Wallet": "Minha Carteira Steam",
    "PurchaseDialog_SteamAccount_Label": "Conta Steam:",
    "PurchaseDialog_BillingInfo_Label": "Endereço de cobrança:",
    "PurchaseDialog_BillingInfo_FirstName": "Nome",
    "PurchaseDialog_BillingInfo_LastName": "Sobrenome",
    "PurchaseDialog_BillingInfo_Address": "Endereço de cobrança",
    "PurchaseDialog_BillingInfo_AddressLine2": "Endereço de cobrança, linha 2",
    "PurchaseDialog_BillingInfo_City": "Cidade",
    "PurchaseDialog_BillingInfo_StateProvince": "Estado/UF/Província",
    "PurchaseDialog_BillingInfo_ZipPostal": "CEP ou código postal",
    "PurchaseDialog_BillingInfo_Country": "País",
    "PurchaseDialog_BillingInfo_SaveInfo": "Salvar o meu endereço para agilizar compras futuras",
    "PurchaseDialog_Action_AddFunds": "Adicionar fundos",
    "PurchaseDialog_Action_Purchase": "Comprar",
    "PurchaseDialog_SSA_Link": "Aceito os termos do %1$s (última atualização em %2$s)",
    "PurchaseDialog_SSA_Link_Title": "Acordo de Assinatura do Steam",
    "PurchaseDialog_SSA_Fail": "Você precisa aceitar os termos do Acordo de Assinatura do Steam para concluir esta transação.",
    "PurchaseDialog_EU_SSA": "Ao clicar em \"Comprar\" você concorda que está recebendo acesso imediato ao conteúdo digital do item e que por esse motivo qualquer possibilidade de anulação da venda resultante termina — a compra é definitiva.",
    "PurchaseDialog_Error_ServerGeneric": "Ocorreu um problema com a compra do seu item. É possível que o anúncio tenha sido removido. Atualize a página e tente novamente.",
    "PurchaseDialog_Error_NoConfirmation": "Ocorreu um problema ao aguardar que confirmasse a compra do item. Atualize a página e tente novamente.",
    "PurchaseDialog_Error_MissingRequired": "Os seguintes campos são obrigatórios:",
    "PurchaseDialog_Error_InvalidMilitaryCity": "Informe um endereço militar válido",
    "PurchaseDialog_Error_InvalidPostal": "Informe um CEP ou código postal válido",
    "PurchaseDialog_PurchaseComplete": "Parabéns pela compra! Você pode ver o novo item no <1>seu inventário</1>.",
    "PurchaseDialog_Button_ViewInventory": "Ver inventário",
    "PurchaseDialog_Confirmation_Title": "Confirmação adicional necessária",
    "PurchaseDialog_Confirmation_Title_Wait": "Aguardando a confirmação da compra...",
    "PurchaseDialog_Confirmation_Body_Mobile": "Algumas compras exigem confirmação pelo aplicativo móvel do Steam.",
    "PurchaseDialog_Confirmation_Body_Email": "Algumas compras exigem confirmação por um e-mail do Steam Guard.",
    "PurchaseDialog_Confirmation_Body_Unknown": "Algumas compras exigem confirmação pelo aplicativo móvel do Steam ou e-mail do Steam Guard.",
    "PurchaseDialog_Confirmation_Description_Mobile": "Use o aplicativo móvel do Steam para confirmar a compra...",
    "PurchaseDialog_Confirmation_Description_Email": "Acesse o seu e-mail para confirmar a compra...",
    "PurchaseDialog_Confirmation_Description_Unknown": "Use o aplicativo móvel do Steam ou acesse o seu e-mail para confirmar a compra...",
    "PurchaseDialog_Purchase_Successful": "Compra concluída com sucesso",
    "PurchaseDialog_Close": "Fechar",
    "PurchaseDialog_ViewInventory": "Ver inventário",
    "PurhcaseDialog_SaveMyAddress": "Salvar o meu endereço para agilizar compras futuras",
    "Listing_NotAvailable": "Este anúncio não está mais disponível",
    "Listing_NotAvailable_Short": "Indisponível",
    "Listing_NotAvailable_Long": "Este anúncio não está mais disponível para compra.",
    "BuyOrderDialog_Header": "Comprar — %1$s",
    "BuyOrderDialog_Header_NoItem": "Encomendar",
    "BuyOrderDialog_BucketPicker_Label": "Que tipo de item deseja comprar?",
    "BuyOrderDialog_BucketPicker_Placeholder": "Selecione um item...",
    "BuyOrderDialog_PriceField": "Que preço deseja pagar:",
    "BuyOrderDialog_PriceField_Suffix": "(por item)",
    "BuyOrderDialog_QuantityField": "Quantos deseja comprar:",
    "BuyOrderDialog_MaxPrice": "Preço máximo %1$s:",
    "BuyOrderDialog_MaxPrice_Tip": "Este é o valor máximo que será cobrado pela sua encomenda. Os itens serão comprados pelo menor preço possível, portanto, a sua encomenda poderá custar menos do que este valor.",
    "BuyOrderDialog_Status_Pending": "Buscando anúncios do item no preço desejado...",
    "BuyOrderDialog_Status_Filled": "Compra bem-sucedida! O item foi adicionado ao seu inventário e o recibo foi enviado para o seu e-mail.",
    "BuyOrderDialog_Status_Settled": "Sucesso! A sua encomenda foi criada.",
    "BuyOrderDialog_Status_Settled_Note": "Você receberá automaticamente uma notificação por e-mail quando a compra for concluída. Você pode cancelar a encomenda na parte superior desta página ou na página inicial do Mercado.",
    "BuyOrderDialog_Status_GenericError": "Ops! Houve um problema ao receber a confirmação dos servidores Steam. Verifique se a sua encomenda foi criada ou processada. Caso contrário, tente novamente mais tarde.",
    "BuyOrderDialog_MinPriceError": "O preço mínimo por unidade é %1$s",
    "OrderBook_Table_PriceOrLess": "≤ %1$s",
    "OrderBook_Table_PriceOrMore": "≥ %1$s",
    "OrderBook_Table_Price": "Preço",
    "OrderBook_Table_Quantity": "Quantidade",
    "OrderBook_SellOrder_Description": "%1$s à venda, a partir de %2$s",
    "OrderBook_SellOrder_Description_None": "Não há anúncios ativos para este item",
    "OrderBook_BuyOrder_Description": "%1$s encomendas por %2$s ou menos",
    "OrderBook_BuyOrder_Description_None": "Não há encomendas ativas para este item.",
    "OrderBook_BuyOrder_NeedBucket": "Selecione um item específico para ver informações de encomenda",
    "OrderBook_Graph_Title": "Encomendas (cumulativo)",
    "OrderBook_Graph_BuyTooltip": "1 encomenda por %2$s ou mais",
    "OrderBook_Graph_BuyTooltip_Plural": "%1$s encomendas por %2$s ou mais",
    "OrderBook_Graph_SellTooltip": "1 anúncio por %2$s ou menos",
    "OrderBook_Graph_SellTooltip_Plural": "%1$s anúncios por %2$s ou menos",
    "OrderBook_PlaceOrder_BuyRequests": "1 encomenda por <1>%2$s</1>",
    "OrderBook_PlaceOrder_BuyRequests_Plural": "%3$s encomendas por <1>%2$s ou menos</1>",
    "MedianSalePrice_Graph_Title": "Valores medianos de venda",
    "Graph_TimeScale_Week": "Semana",
    "Graph_TimeScale_Month": "Mês",
    "Graph_TimeScale_Year": "Ano",
    "Graph_TimeScale_Lifetime": "Desde o início",
    "Graph_NumberSold": "%1$s vendido(s)",
    "Graph_Label_Price": "Preço",
    "Graph_Label_Volume": "Quantidade",
    "Graph_NoData": "Sem dados para o período selecionado",
    "Graph_Tooltip_NoPurchaseData": "Sem dados de compra",
    "Graph_Tooltip_NA": "N/D",
    "MyOrders_GridHeader_Name": "NOME",
    "MyOrders_GridHeader_Price": "PREÇO",
    "MyOrders_GridHeader_Quantity": "QUANTIDADE",
    "MyOrders_GridHeader_DateListed": "ANUNCIADO EM",
    "MyOrders_Cancel": "Cancelar",
    "MyOrders_Remove": "Remover",
    "MyOrders_Heading": "Meus anúncios e encomendas ativos",
    "MyOrders_Heading_Sell": "Anúncios",
    "MyOrders_Heading_Buy": "Encomendas",
    "MyOrders_Heading_MyPurchaseOffers": "Compras: minhas encomendas",
    "MyOrders_Heading_MyListings": "Vendas: meus anúncios",
    "MyOrders_FailedToLoad": "Houve um problema ao carregar os dados deste item.",
    "MyOrders_NoActiveOrders_Item": "Você não tem anúncios nem encomendas ativas para este item.",
    "MyOrders_NoBuyOrders_Item": "Você não tem encomendas ativas para este item.",
    "MyOrders_NoSellOrders_Item": "Você não tem anúncios ativos para este item. Venda itens pelo seu inventário ou clicando no botão \"Vender\" nesta página.",
    "CancelBuyOrder_GenericError": "Houve um problema ao cancelar a sua encomenda. Tente novamente mais tarde.",
    "CancelListing_GenericError": "Houve um problema ao remover o seu anúncio. Tente novamente mais tarde.",
    "CancelListing_Dialog_Header": "Remover um anúncio",
    "CancelListing_Dialog_Prompt": "Tem certeza de que deseja remover o anúncio de %1$s e devolver o item ao seu inventário?",
    "CancelListing_Dialog_Prompt_Generic": "Tem certeza de que deseja remover o anúncio e devolver o item ao seu inventário?",
    "CancelListing_Dialog_Yes": "Sim, remover anúncio",
    "CancelListing_Dialog_No": "Não",
    "CancelListing_Dialog_Success": "Anúncio removido com sucesso",
    "SellDialog_Frame_Title": "Escolha um item do seu inventário",
    "UniqueBuyOrder_Explanation_Header": "O que é uma encomenda?",
    "UniqueBuyOrder_Explanation_1": "Defina o seu preço preferido, e a compra será realizada automaticamente quando o item estiver disponível pelo preço escolhido.",
    "UniqueBuyOrder_Explanation_2": "O Steam garantirá que você pague o melhor preço disponível.",
    "UniqueBuyOrder_Explanation_3": "Para este item, encomendas serão processadas com a opção de compra mais barata, não importando as suas características.",
    "Error_Sorry": "Ops!",
    "Error_Encountered": "Ocorreu um erro ao processar a sua solicitação:",
    "Error_TooManyRequests_Description": "Você realizou solicitações demais recentemente. Aguarde e tente realizar a sua solicitação novamente mais tarde.",
    "Container_ContentsLabel": "Pode conter:",
    "Error_LoadingContent": "Houve um problema ao carregar este conteúdo",
    "Error_LoadingMarketItem": "O item solicitado pode não existir ou um problema temporário pode estar impedindo o seu carregamento. Tente novamente mais tarde.",
    "ListingFilter_Title": "Filtrar anúncios",
    "Listings_NoneFound": "Nenhum anúncio encontrado",
    "AssetProperty_Range_MinPlaceholder": "Mín.",
    "AssetProperty_Range_MaxPlaceholder": "Máx.",
    "Accessories_FieldSectionLabel": "Acessórios",
    "Item_CountryBuySellRestricted": "Você não pode comprar este item porque a compra e venda deste tipo de item está indisponível em seu país.",
    "Item_CountryBuyRestricted": "Você não pode comprar este item porque a compra deste tipo de item está indisponível em seu país.",
    "Listing_EnhancedAppearance_Missing": "Este anúncio ainda não tem imagens únicas ou aprimoradas. A imagem aqui exibida pode variar ligeiramente do item anunciado.",
    "Listing_EnhancedAppearance_ShowBackground": "Exibir fundo",
    "Unavailable_Header": "Você não pode comprar nem vender itens no Mercado pelo seguinte motivo:",
    "Unavailable_Header_Plural": "Você não pode comprar nem vender itens no Mercado pelos seguintes motivos:",
    "Economy_Market_TopLevelReason_AccountLocked": "A sua conta está atualmente trancada.",
    "Economy_Market_TopLevelTooltip_AccountLocked": "Informações sobre este trancamento podem ser encontradas ao clicar na barra vermelha exibida no canto superior direito após iniciar a sessão no cliente Steam.  Para informações adicionais, entre em contato com o Suporte Steam.",
    "Economy_Market_HeaderTip_AccountLocked": "A sua conta está atualmente trancada. Informações sobre este trancamento podem ser encontradas ao clicar na barra vermelha exibida no canto superior direito após iniciar a sessão no cliente Steam.",
    "Economy_Market_TopLevelTooltip_RemoveRestrictionLink": "Para remover esta restrição...",
    "Economy_Market_TopLevelReason_AccountTradeBanned": "A sua conta está atualmente proibida de trocar.",
    "Economy_Market_TopLevelTooltip_AccountTradeBanned": "A proibição pode ser temporária (com duração variável) ou permanente. Para saber quando (e se) poderá voltar a trocar, clique na barra vermelha exibida no canto superior direito após iniciar a sessão no cliente Steam.",
    "Economy_Market_HeaderTip_AccountTradeBanned": "A sua conta foi proibida de trocar. Para saber quando poderá voltar a trocar, clique na barra vermelha exibida no canto superior direito após iniciar a sessão no cliente Steam.",
    "Economy_Market_TopLevelTooltip_MoreInfoLink": "Mais informações...",
    "Economy_Market_TopLevelReason_AccountNotTrusted": "É necessário ter realizado uma compra no Steam há mais de %1$s dias, mas há menos de um ano, sem estornos ou disputas de pagamento recentes.",
    "Economy_Market_TopLevelTooltip_AccountNotTrusted": "Realize uma compra na Loja Steam. Crédito da Carteira, jogos e conteúdos adicionais são compras válidas — já a ativação de códigos de produto e presentes não são compras válidas. O Suporte Steam não pode remover tal restrição.",
    "Economy_Market_HeaderTip_AccountNotTrusted": "É necessário ter realizado uma compra no Steam há mais de %1$s dias, mas há menos de um ano, sem estornos ou disputas de pagamento recentes. O Suporte Steam não pode remover estas restrições.",
    "Economy_Market_TopLevelReason_AccountNotTrusted_Waiting": "Parece que você realizou uma compra válida na Loja Steam, mas ainda não completou %1$s dias.",
    "Economy_Market_TTopLevelTooltip_AccountNotTrusted_Waiting": "É necessário ter realizado uma compra válida no Steam entre %1$s dias e um ano, sem estornos ou disputas de pagamento recentes. Parece que você realizou uma compra, mas a mesma ainda não completou %1$s dias. O Suporte Steam não pode remover tal restrição.",
    "Economy_Market_TopLevelReason_AccountPasswordRecentlyReset": "A senha da sua conta foi redefinida recentemente.",
    "Economy_Market_TopLevelTooltip_AccountPasswordRecentlyReset": "Esta restrição será removida automaticamente %1$s dias após a última redefinição de senha da conta, ou %2$s dias caso a conta não tenha sido usada por muito tempo. Apenas o processo de redefinição de senha por tê-la esquecido implica nesta restrição. Alterá-la por si só não implica em restrições. O Suporte Steam não pode remover quaisquer restrições.",
    "Economy_Market_HeaderTip_AccountPasswordRecentlyReset": "A senha da sua conta Steam foi redefinida recentemente. Para ajudar a proteger usuários que podem ter tido a sua conta de e-mail comprometida, acesso ao Mercado da Comunidade por será restrito por %1$s dias após uma redefinição de senha.",
    "Economy_Market_HeaderTip_NewPaymentMethod_NoDate": "Você adicionou fundos à sua Carteira Steam recentemente com um cartão de crédito não verificado cujo uso aumentou nos últimos dias. Você pode tentar <1>verificar os fundos agora</1> ou aguardar a remoção automática da restrição.\n\nOBS.: a verificação de fundos pode não funcionar com todos os bancos ou cartões de crédito. Caso não consiga verificar o seu cartão, você precisará esperar até que a forma de pagamento seja verificada pelo Steam. O Suporte Steam não pode fornecer ou converter os valores de verificação, nem remover tal restrição.",
    "Economy_Market_HeaderTip_AccountHasNewPaymentMethod": "Você adicionou fundos à sua Carteira Steam recentemente com PayPal ou uma forma de pagamento não verificada cujo uso aumentou nos últimos dias. Você não poderá usar o Mercado por alguns dias enquanto os fundos são verificados.",
    "Economy_Market_TopLevelReason_AccountHasNewPaymentMethod": "Você adicionou fundos à sua Carteira Steam recentemente usando uma nova conta PayPal ou uma forma de pagamento cujo uso aumentou nos últimos dias. Você não poderá usar o Mercado por alguns dias enquanto os fundos são verificados.",
    "Economy_Market_TopLevelReason_AcceptedWalletGift": "Você aceitou um vale-presente digital de um amigo recentemente.",
    "Economy_Market_HeaderTip_AcceptedWalletGift": "Você aceitou um vale-presente digital de um amigo recentemente. Não será possível usar o Mercado da Comunidade Steam nos primeiros %1$s dias após a compra do vale-presente.",
    "Economy_Market_TopLevelReason_InvalidCookie": "O Steam está tendo problemas com os cookies do seu navegador.",
    "Economy_Market_TopLevelTooltip_InvalidCookie": "O seu cookie parece ser inválido. Tente finalizar a sessão no Steam e iniciá-la novamente. Além disso, verifique se os cookies estão ativados no seu navegador e que não há extensões interferindo com o cookie do Steam.",
    "Economy_Market_HeaderTip_InvalidCookie": "O seu navegador pode estar com cookies desativados. Verifique se todos os cookies são permitidos pelo seu navegador e, então, tente finalizar a sessão e iniciá-la novamente.",
    "Economy_Market_TopLevelReason_NewDevice": "Você está acessando o Mercado de um dispositivo não protegido pelo Steam Guard por %1$s dias.",
    "Economy_Market_TopLevelTooltip_NewDevice": "Caso tenha um dispositivo já verificado, você poderá usar o Mercado no mesmo. Caso contrário, você precisará aguardar até que verifiquemos este dispositivo para usar o Mercado.",
    "Economy_Market_HeaderTip_NewDevice": "Você iniciou a sessão em um novo dispositivo ou navegador. Para proteger os itens no seu inventário, você não poderá usar o Mercado neste dispositivo por %1$s dias.",
    "Economy_Market_TopLevelReason_SelfRefund": "Você reembolsou uma transação para a sua Carteira Steam recentemente.",
    "Economy_Market_TopLevelTooltip_SelfRefund": "Você não poderá usar o Mercado nos %1$s dias seguintes ao seu autorrembolso mais recente. O Suporte Steam não pode remover quaisquer restrições.",
    "Economy_Market_HeaderTip_SelfRefund": "Você recentemente reembolsou uma transação em troca de créditos da Carteira Steam. Você não poderá usar o Mercado nos %1$s dias seguintes ao seu autorrembolso mais recente.",
    "Economy_Market_TopLevelReason_LimitedUser": "A sua conta é limitada.",
    "Economy_Market_TopLevelTooltip_LimitedUser": "A sua conta é limitada e não tem acesso a certos recursos do Steam, incluindo o Mercado da Comunidade.",
    "Economy_Market_HeaderTip_LimitedUser": "A sua conta é limitada e não tem acesso a certos recursos do Steam, incluindo o Mercado da Comunidade.",
    "Economy_Market_HeaderTip_SteamGuardOnlyRecentlyEnabled": "Você redefiniu ou ativou o Steam Guard recentemente e poderá usar o Mercado %1$s dias após a ativação do Steam Guard.",
    "Economy_Market_TopLevelTooltip_SteamGuardRecentlyEnabled": "Você precisa aguardar até que o Steam Guard esteja ativado na sua conta por 15 dias. O Suporte Steam não pode remover tal restrição.",
    "Economy_Market_TopLevelReason_NoSteamGuard": "A sua conta precisa estar protegida pelo Steam Guard por pelo menos %1$s dias.",
    "Economy_Market_TopLevelTooltip_SteamGuardDisabled": "Ative o Steam Guard na sua conta. Confirme que o seu endereço de e-mail foi verificado e você já tenha iniciado a sessão com a sua conta após a ativação do Steam Guard.",
    "Economy_Market_HeaderTip_NoSteamGuard": "A sua conta precisa estar protegida pelo Steam Guard por pelo menos %1$s dias."
}
