{
    "footer_legal_notice": "© %1$s Valve Corporation. Усі права застережено. Усі торговельні марки є власністю відповідних власників у США та інших країнах. <br>ПДВ включено в ціну (якщо застосовно).",
    "footer_link_header_steam": "STEAM",
    "footer_link_header_valve": "VALVE",
    "footer_link_header_legal": "ЮРИДИЧНА ІНФОРМАЦІЯ",
    "footer_link_header_more": "БІЛЬШЕ",
    "footer_link_about_steam": "Про Steam",
    "footer_link_steam_ssa": "Угода підписника Steam",
    "footer_link_steamworks": "Steamworks",
    "footer_link_steam_distribution": "Розповсюдження у Steam",
    "footer_link_gift_cards": "Подарункові картки",
    "footer_link_about_valve": "Про Valve",
    "footer_link_jobs": "Вакансії",
    "footer_link_hardware": "Обладнання",
    "footer_link_recycling": "Переробка",
    "footer_link_privacy": "Приватність",
    "footer_link_accessibility": "Доступність",
    "footer_link_notices_and_policies": "Політика та документи",
    "footer_link_cookies": "Файли cookie",
    "footer_link_refunds": "Повернення коштів",
    "footer_link_get_steam": "Завантажити Steam",
    "footer_link_get_mobile_apps": "Завантажити мобільні застосунки",
    "footer_link_get_support": "Підтримка",
    "footer_link_my_account": "Мій акаунт",
    "footer_view_mobile_website": "Мобільна версія"
}
