{
    "moderation_moderatorlevel_any": "Moderador",
    "moderation_moderatorlevel_supervisor": "Supervisor",
    "moderation_moderatorlevel_valveadmin": "Administrador de Valve",
    "moderation_moderatorlevel_unknown": "Desconocido",
    "moderation_chatmetadataerror": "No se pudieron recuperar los metadatos de esta denuncia de chat (error: %1$s)",
    "moderation_friendsforduration": "por %1$s",
    "moderation_friends_label": "Amigos:",
    "moderation_chatduration_label": "Duración del chat antes de la denuncia:",
    "moderation_senderip_label": "IP del remitente:",
    "moderation_firstchatted_label": "Primer mensaje de chat (aproximado):",
    "moderation_reported_message": "Mensaje denunciado",
    "moderation_toggle_bbcode": "Activar o desactivar BBCode",
    "moderation_image_removed": "Imagen eliminada",
    "moderation_image_obscured": "Visible al pasar el cursor",
    "moderation_reported_time_label": "Denunciados:",
    "moderation_network_firstused_time": "Proveedor de servicios de internet (ISP) usado por primera vez en este chat hace %1$s",
    "moderation_recentchatrooms_label": "Salas de chat recientes:",
    "moderation_groupname_label": "Nombre del grupo:",
    "moderation_roomname_label": "Nombre de la sala:",
    "moderation_recentchatpartners_label": "Chats recientes con:",
    "moderation_chat_reportedmessagesfrom": "Mensajes denunciados enviados por %1$s",
    "moderation_chatgroup_reportedmessagesfrom": "Mensajes de grupo denunciados enviados por %1$s",
    "moderation_chatgroup_defaultroom": "Predeterminado",
    "moderation_chatgroup_reports": "Denuncias del chat de grupo \"%1$s\"",
    "moderation_chatgroup_membercount": "Miembros:",
    "moderation_chatgroup_chatrooms": "Salas:",
    "moderation_chatgroup_disabled": "DESACTIVADA",
    "moderation_chatgroup_tagline": "Lema:",
    "moderation_chatgroup_type": "Tipo de grupo:",
    "moderation_chatgroup_owner": "Propietario:",
    "moderation_chatgroup_type_privateadhoc": "Privado ad hoc (id. de grupo %1$s)",
    "moderation_chatgroup_type_app": "Aplicación creada (id. de aplicación %1$s)",
    "moderation_chatgroup_type_clanapp": "Grupo oficial de la aplicación en la comunidad (id. de clan %1$s)",
    "moderation_chatgroup_type_clanpublic": "Público - Clan: %1$s (id. de clan %2$s)",
    "moderation_chatgroup_type_clanprivate": "Privado - Clan: %1$s (id. de clan %2$s)",
    "moderation_num_selected": "%1$s seleccionado",
    "moderation_select_all_unresolved": "Todas sin resolver",
    "moderation_select_none": "Ninguna",
    "moderation_actions_acquit": "Absolver",
    "moderation_actions_acquit_multiple": "Absolver (%1$s)",
    "moderation_actions_sanction": "Sancionar...",
    "moderation_actions_sanction_multiple": "Sancionar... (%1$s)",
    "moderation_actions_escalate": "Escalar...",
    "moderation_actions_escalate_multiple": "Escalar... (%1$s)",
    "moderation_actions_confirmsanction": "Confirmar sanción",
    "moderation_actions_confirmsanction_multiple": "Confirmar sanción (%1$s)",
    "moderation_actions_lockthread": "Cerrar hilo",
    "moderation_actions_lockthread_multiple": "Cerrar hilo (%1$s)",
    "moderation_actions_unlockthread": "Abrir hilo",
    "moderation_actions_unlockthread_multiple": "Abrir hilo (%1$s)",
    "moderation_actions_sustain": "Mantener la moderación",
    "moderation_actions_sustain_multiple": "Mantener la moderación (%1$s)",
    "moderation_actions_suspicious": "Marcar como sospechoso",
    "moderation_actions_suspicious_multiple": "Marcar como sospechoso (%1$s)",
    "moderation_actions_unknown": "Desconocida",
    "moderation_moderator_level": "Tu nivel de moderador: %1$s",
    "moderation_claim_subjects": "Reclamar asuntos",
    "moderation_claim_more": "¿Deseas reclamar más?",
    "moderation_claim_more_desc": "No tienes más denuncias que resolver. ¿Deseas reclamar más?",
    "moderation_claim_batch_desc": "Reclamar lote de la mayor prioridad:",
    "moderation_claim_amount": "Reclamar (%1$s)",
    "moderation_claim_escalated_amount": "Reclamo escalado (%1$s)",
    "moderation_claim_valve_amount": "Reclamar solo de Valve (%1$s)",
    "moderation_claim_reports": "Reclamar...",
    "moderation_release_reports": "Lanzar todos",
    "moderation_moderatoractions_next": "Próx.",
    "moderation_moderatoractions_moderate": "Moderar",
    "moderation_moderatoractions_ok": "Aceptar",
    "moderation_escalation_description": "Choose level to escalate to:",
    "moderation_escalation_title": "Escalar %1$s asunto",
    "moderation_escalation_title_Plural": "Escalar %1$s asuntos",
    "moderation_escalation_reason_select": "Seleccionar razón para escalamiento",
    "moderation_escalation_reason_label": "Razón:",
    "moderation_escalation_escalate": "Escalar",
    "moderation_escalationlevel_any": "Cualquier moderador",
    "moderation_escalationlevel_supervisor": "Supervisor",
    "moderation_escalationlevel_valve": "Valve",
    "moderation_escalationlevel_valve_desc": "Solo para Valve",
    "moderation_escalationlevel_supervisor_desc": "Se requiere un supervisor",
    "moderation_chatmetadata_deleted": "Los metadatos asociados a este informe de chat se eliminaron debido a su antigüedad. Solo se conservan durante unos 21 días.",
    "moderation_chatmetadata_futurelogcollection": "Este registro del chat puede mejorarse con mensajes adicionales enviados después de la denuncia dentro de %1$s",
    "moderation_resolutionaction_removed": "Eliminar el contenido denunciado",
    "moderation_resolutionaction_relabelled": "Reclasificar el contenido denunciado",
    "moderation_resolutionaction_suspicious": "Bloquear la cuenta por publicar contenido sospechoso",
    "moderation_resolutionaction_harassmentstrike": "Agregar una infracción por acoso",
    "moderation_resolutionaction_unknownvalue": "Desconocido (%1$s)",
    "moderation_resolutionaction_removeandwarn": "Eliminar y advertir al usuario",
    "moderation_resolutionaction_removeandban": "Eliminar y bloquear el acceso al punto de encuentro",
    "moderation_resolutionaction_removeandkick": "Eliminar y expulsar del grupo",
    "moderation_resolutionstatus_sanctioned": "Sancionado",
    "moderation_resolutionstatus_acquitted": "Absuelto",
    "moderation_subjectgroupsummary_chatmsg": "%1$s denuncias en %2$s mensajes de \"%3$s\"",
    "moderation_subjectgroupsummary_chatgroup": "%1$s denuncias en %2$s mensajes de \"%3$s\"",
    "subject_count": "(1 asunto)",
    "subject_count_Plural": "(%1$s asuntos)",
    "moderation_sanction_commenthistorydeleted_forever": "Todas las publicaciones eliminadas",
    "moderation_sanction_commenthistorydeleted": "Se eliminaron las publicaciones de los últimos %1$s días",
    "moderation_sanction_communitybanned_forever": "Bloqueado permanentemente de la comunidad",
    "moderation_sanction_communitybanned": "Bloqueado de la comunidad por %1$s días",
    "moderation_sanction_deleted": "Contenido denunciado eliminado",
    "moderation_sanction_hubbanned_forever": "Bloqueado permanentemente del punto de encuentro",
    "moderation_sanction_hubbanned": "Bloqueado del punto de encuentro por %1$s días",
    "moderation_sanction_markassuspicious": "Marcado como sospechoso",
    "moderation_sanction_relabelled": "Reetiquetado",
    "moderation_sanction_tradebanned_forever": "Intercambios bloqueados permanentemente",
    "moderation_sanction_tradebanned": "Intercambios bloqueados por %1$s días",
    "moderation_sanction_kickedfromgroup": "Expulsado del grupo",
    "moderation_sanction_unknown": "Sin determinar",
    "originalresolution_acquitted": "Absuelto en la primera moderación",
    "originalresolution_sanctioned": "Sancionado en la primera moderación",
    "has_trade_offer": "Este tema tiene una oferta de intercambio adjunta",
    "subjectauditlog_noentries": "No entries",
    "subjectauditlog_error": "Error: Failed to load audit log.",
    "reasonlist_title": "Reasons:",
    "reasonlist_reasonwithcount": "%1$s (%2$s)",
    "contentreportslist_noreports": "No reports",
    "contentreportslist_acquitted_at": "Acquitted at %1$s",
    "contentreportslist_resolved_at": "Resolved at %1$s",
    "contentreportslist_disputed_at": "Disputed at %1$s",
    "contentreportslist_dispute_resolved_at": "Dispute resolved at %1$s",
    "commentsanctiondialog_selectreason": "Click to select...",
    "commentsanctiondialog_moderate": "Moderate",
    "reportedsubjectlist_header": "Reported subjects",
    "empty_no_trailing_comma": ""
}
