{
    "footer_legal_notice": "© %1$s Valve Corporation. Alle rettigheder forbeholdes. Alle varemærker tilhører deres respektive ejere i USA og andre lande.<br>Moms inkluderet i alle priser, hvor det er gældende.",
    "footer_link_header_steam": "STEAM",
    "footer_link_header_valve": "VALVE",
    "footer_link_header_legal": "JURIDISK",
    "footer_link_header_more": "MERE",
    "footer_link_about_steam": "Om Steam",
    "footer_link_steam_ssa": "Steam-abonnentaftale",
    "footer_link_steamworks": "Steamworks",
    "footer_link_steam_distribution": "Distribution på Steam",
    "footer_link_gift_cards": "Gavekort",
    "footer_link_about_valve": "Om Valve",
    "footer_link_jobs": "Karriere",
    "footer_link_hardware": "Hardware",
    "footer_link_recycling": "Genbrug",
    "footer_link_privacy": "Privatliv",
    "footer_link_accessibility": "Tilgængelighed",
    "footer_link_notices_and_policies": "Meddelelser og politikker",
    "footer_link_cookies": "Cookies",
    "footer_link_refunds": "Refunderinger",
    "footer_link_get_steam": "Hent Steam",
    "footer_link_get_mobile_apps": "Hent mobilapps",
    "footer_link_get_support": "Kundesupport",
    "footer_link_my_account": "Min konto",
    "footer_view_mobile_website": "Vis mobilside"
}
