{
    "footer_legal_notice": "© %1$s Valve Corporation. Alla rättigheter förbehållna. Alla varumärken tillhör sina respektive ägare i USA och andra länder.<br>Moms ingår i alla priser där det är tillämpligt.",
    "footer_link_header_steam": "STEAM",
    "footer_link_header_valve": "VALVE",
    "footer_link_header_legal": "JURIDISKT",
    "footer_link_header_more": "MER",
    "footer_link_about_steam": "Om Steam",
    "footer_link_steam_ssa": "Steams abonnentavtal",
    "footer_link_steamworks": "Steamworks",
    "footer_link_steam_distribution": "Distribution på Steam",
    "footer_link_gift_cards": "Presentkort",
    "footer_link_about_valve": "Om Valve",
    "footer_link_jobs": "Jobb",
    "footer_link_hardware": "Maskinvara",
    "footer_link_recycling": "Återvinning",
    "footer_link_privacy": "Sekretess",
    "footer_link_accessibility": "Tillgänglighet",
    "footer_link_notices_and_policies": "Meddelanden och policyer",
    "footer_link_cookies": "Cookies",
    "footer_link_refunds": "Återbetalningar",
    "footer_link_get_steam": "Hämta Steam",
    "footer_link_get_mobile_apps": "Hämta mobilappar",
    "footer_link_get_support": "Kundsupport",
    "footer_link_my_account": "Mitt konto",
    "footer_view_mobile_website": "Visa mobilsida"
}
