{
    "AppPage_PurchaseOptions_Title": "TÙY CHỌN MUA HÀNG",
    "AppPage_BuyThisBundle": "Mua bộ này để tiết kiệm %2$s% cho các sản phẩm còn lại!",
    "AppPage_BuyThisBundle_Plural": "Mua bộ này để tiết kiệm %2$s% cho tất cả %1$s sản phẩm!",
    "AppPage_BuyThisBundle_Partial": "Mua bộ này để tiết kiệm %2$s% trên sản phẩm bạn chưa có!",
    "AppPage_BuyThisBundle_Partial_Plural": "Mua bộ này để tiết kiệm %2$s% trên %1$s sản phẩm bạn chưa có!",
    "AppPage_CollectionComplete": "Bộ sưu tập hoàn thành! %1$s trên %1$s sản phẩm từ bộ sưu tập này đã nằm trong thư viện của bạn.",
    "AppPage_CollectionComplete_Plural": "Bộ sưu tập hoàn thành! %1$s trên %1$s sản phẩm từ bộ sưu tập này đã nằm trong thư viện của bạn.",
    "AppPage_AdditionalItems": "Và thêm %1$s sản phẩm",
    "AppPage_PurchaseOption_DownloadDemo": "Tải xuống %1$s",
    "AppPage_PurchaseOption_Bundle": "BỘ",
    "AppPage_PurchaseOption_InLibrary": "TRONG THƯ VIỆN",
    "AppPage_PurchaseOption_CompleteYourCollection": "HOÀN THIỆN BỘ SƯU TẬP CỦA BẠN",
    "AppPage_PurchaseOption_InCart": "TRONG GIỎ HÀNG",
    "AppPage_PurchaseOption_Play": "Chơi %1$s",
    "AppPage_PurchaseOption_Play_Description": "%1$s đã ở trong thư viện Steam của bạn",
    "AppPage_PurchaseOption_FreeToPlay": "Chơi miễn phí",
    "AppPage_PurchaseOption_FreeDemo": "Demo miễn phí",
    "AppPage_PurchaseOption_FreeWeekend": "Chơi miễn phí đến %1$s",
    "AppPage_PurchaseOption_GetFreeToKeep": "Nhận %1$s",
    "AppPage_PurchaseOption_FreeToKeepDescription": "Bạn có thể nhận miễn phí trước %1$s. Một vài hạn chế được áp dụng.",
    "AppPage_PurchaseOption_IncludedWithMasterSub": "Đi kèm với đăng ký <1>%1$s</1> của bạn.",
    "AppPage_PurchaseOption_JoinPlaytest": "Tham gia %1$s",
    "AppPage_PurchaseOption_JoinPlaytest_Description": "Yêu cầu truy cập và bạn sẽ được báo khi nhà phát triển sẵn sàng cho nhiều người tham gia hơn.",
    "AppPage_PurchaseOption_JoinPlaytest_InvitePending": "Bạn đã yêu cầu truy cập! Nhớ để ý email thông báo từ Steam để biết khi nào nhà phát triển sẵn sàng nhận thêm người tham gia.",
    "AppPage_PurchaseOption_Playtest_Accepted_Title": "Chơi %1$s ngay!",
    "AppPage_PurchaseOption_Playtest_Accepted": "Bạn đã được mời tham gia! Nhấn nút cài đặt và khởi động nào.",
    "AppPage_PurchaseOption_Playtest_Accepted_Unavailable_Title": "Bạn nằm trong %1$s",
    "AppPage_PurchaseOption_Playtest_Accepted_Unavailable": "Đợt Playtest này đang ngừng hoạt động. Dõi theo các kế hoạch thử nghiệm sắp tới từ nhà phát triển nhé.",
    "AppPage_PurchaseOption_Playtest_Open_Unreleased": "Playtest sẽ được thêm vào thư viện Steam của bạn khi ra mắt. Dõi theo các kế hoạch thử nghiệm sắp tới từ nhà phát triển nhé.",
    "AppPage_PurchaseOption_Playtest_Open": "Playtest này đã được thêm vào thư viện Steam của bạn.",
    "AppPage_Prepurchase": "Mua trước %1$s",
    "AppPage_Dropdown_DefaultTitle": "Mua %1$s",
    "AppPage_Dropdown_DefaultDescription_Subscription": "Được tính trên cơ sở định kỳ.",
    "AppPage_PurchaseOption_JoinPlaytest_InvitedByFriend": "Một người bạn đã mời bạn tham gia Playtest này.",
    "AppPage_PurchaseOption_AddToCart": "THÊM VÀO GIỎ HÀNG",
    "AppPage_PurchaseOption_PlayNow": "CHƠI",
    "AppPage_PurchaseOption_MoreInfo": "THÔNG TIN",
    "AppPage_PurchaseOption_BundleInfo": "THÔNG TIN BỘ SẢN PHẨM",
    "AppPage_PurchaseOption_CompareEditions": "SO SÁNH CÁC PHIÊN BẢN",
    "AppPage_PurchaseOption_AddToLibrary": "THÊM VÀO THƯ VIỆN",
    "AppPage_PurchaseOption_Download": "TẢI XUỐNG",
    "AppPage_PurchaseOption_AddedToLibrary": "%1$s đã được thêm vào tài khoản của bạn. Bạn có thể truy cập trong thư viện Steam của mình.",
    "AppPage_PurchaseOption_AddToLibraryError": "Không thể thêm %1$s vào tài khoản của bạn. (%2$s)",
    "AppPage_SummaryBar_SteamDeckCompat": "TƯƠNG THÍCH VỚI STEAM DECK",
    "AppPage_SummaryBar_UserTags": "NHÃN NGƯỜI DÙNG",
    "AppPage_SummaryBar_UserReviews": "ĐÁNH GIÁ",
    "AppPage_SummaryBar_GameInfo": "THÔNG TIN TRÒ CHƠI",
    "AppPage_SummaryBar_Developer": "Nhà phát triển",
    "AppPage_SummaryBar_Publisher": "Nhà phát hành",
    "AppPage_SummaryBar_ReleaseDate": "Phát hành",
    "AppPage_Reviews_AllTime": "MỌI LÚC:",
    "AppPage_Reviews_Recent": "GẦN ĐÂY:",
    "AppPage_ReviewStats": "%1$s% trên %2$s",
    "AppPage_Discount_Last30": "Giảm giá dựa trên giá thấp nhất trong 30 ngày qua",
    "AppPage_AdvanceAccess_Banner": "TRUY CẬP ƯU TIÊN BẮT ĐẦU VÀO %1$s",
    "AppPage_AdvanceAccess_Starts": "Mua trước phiên bản này và thưởng thức trò chơi %2$s trước thời điểm phát hành chính thức. Bắt đầu sau khoảng %1$s.",
    "AppPage_AdvanceAccess_Now": "Mua phiên bản này và thưởng thức trò chơi ngay, trước ngày phát hành chính thức.",
    "AppPage_AdvanceAccess_Starts_Owned": "Bạn sẽ có thể chơi trò chơi %2$s trước ngày phát hành chính thức thông qua truy cập ưu tiên. Bắt đầu trong khoảng %1$s.",
    "AppPage_AdvanceAccess_Now_Owned": "Chơi ngay! Bạn có thể chơi trò chơi này thông qua truy cập ưu tiên trước ngày phát hành chính thức.",
    "discount_desc_mastersub": "Tiết kiệm %2$s% với %3$s khi mua %4$s cho tài khoản của bạn",
    "discount_desc_preset_special": "ƯU ĐÃI ĐẶC BIỆT! Kết thúc trong %1$s",
    "discount_desc_preset_special_date": "ƯU ĐÃI ĐẶC BIỆT! Kết thúc vào %1$s",
    "discount_desc_preset_weekend": "ƯU ĐÃI CUỐI TUẦN! Kết thúc trong %1$s",
    "discount_desc_preset_weekend_date": "ƯU ĐÃI CUỐI TUẦN! Kết thúc vào %1$s",
    "discount_desc_preset_daily": "ƯU ĐÃI HẰNG NGÀY! Kết thúc trong %1$s",
    "discount_desc_preset_daily_date": "ƯU ĐÃI HẰNG NGÀY! Kết thúc vào %1$s",
    "discount_desc_preset_midweek": "ƯU ĐÃI GIỮA TUẦN! Kết thúc trong %1$s",
    "discount_desc_preset_midweek_date": "ƯU ĐÃI GIỮA TUẦN! Kết thúc vào %1$s",
    "discount_desc_limited_time": "Ưu đãi có thời hạn",
    "discount_desc_limited_time_date": "Ưu đãi có thời hạn",
    "discount_desc_preset_loyalty": "ƯU ĐÃI TRI ÂN KHÁCH HÀNG! Kết thúc trong %1$s",
    "discount_desc_preset_loyalty_date": "ƯU ĐÃI TRI ÂN KHÁCH HÀNG! Kết thúc vào %1$s",
    "discount_desc_preset_promotion": "GIÁ ƯU ĐÃI! Kết thúc trong %1$s",
    "discount_desc_preset_promotion_date": "GIÁ ƯU ĐÃI! Kết thúc vào %1$s",
    "discount_desc_preset_halloween": "GIẢM GIÁ HALLOWEEN! Kết thúc trong %1$s",
    "discount_desc_preset_mystery_midweek": "ƯU ĐÃI BÍ ẨN GIỮA TUẦN! Kết thúc trong %1$s",
    "discount_desc_preset_cyberpunk_midweek": "ƯU ĐÃI CYBERPUNK GIỮA TUẦN! Kết thúc trong %1$s",
    "discount_desc_preset_halloween_date": "GIẢM GIÁ HALLOWEEN! Kết thúc vào %1$s",
    "discount_desc_preset_autumn": "GIẢM GIÁ MÙA THU! Kết thúc trong %1$s",
    "discount_desc_preset_autumn_date": "GIẢM GIÁ MÙA THU! Kết thúc vào %1$s",
    "discount_desc_preset_holiday": "GIẢM GIÁ NGÀY LỄ! Kết thúc trong %1$s",
    "discount_desc_preset_holiday_date": "GIẢM GIÁ NGÀY LỄ! Kết thúc vào %1$s",
    "discount_desc_preset_summer": "GIẢM GIÁ MÙA HÈ! Kết thúc trong %1$s",
    "discount_desc_preset_summer_date": "GIẢM GIÁ MÙA HÈ! Kết thúc vào %1$s",
    "discount_desc_preset_flash_6": "ƯU ĐÃI CHỚP NHOÁNG! Kết thúc trong %1$s",
    "discount_desc_preset_flash_6_date": "ƯU ĐÃI CHỚP NHOÁNG! Kết thúc vào %1$s",
    "discount_desc_preset_flash_8": "ƯU ĐÃI CHỚP NHOÁNG! Kết thúc trong %1$s",
    "discount_desc_preset_flash_8_date": "ƯU ĐÃI CHỚP NHOÁNG! Kết thúc vào %1$s",
    "discount_desc_preset_flash_10": "ƯU ĐÃI CHỚP NHOÁNG! Kết thúc trong %1$s",
    "discount_desc_preset_flash_10_date": "ƯU ĐÃI CHỚP NHOÁNG! Kết thúc vào %1$s",
    "discount_desc_preset_flash_12": "ƯU ĐÃI CHỚP NHOÁNG! Kết thúc trong %1$s",
    "discount_desc_preset_flash_12_date": "ƯU ĐÃI CHỚP NHOÁNG! Kết thúc vào %1$s",
    "discount_desc_preset_vote": "ƯU ĐÃI ĐẶC BIỆT! Kết thúc trong %1$s",
    "discount_desc_preset_vote_date": "ƯU ĐÃI ĐẶC BIỆT! Kết thúc vào %1$s",
    "discount_desc_preset_publisher": "GÓI NHÀ PHÁT HÀNH! Kết thúc trong %1$s",
    "discount_desc_preset_publisher_date": "GÓI NHÀ PHÁT HÀNH! Kết thúc vào %1$s",
    "discount_desc_preset_weeklong": "ƯU ĐÃI XUYÊN TUẦN! Kết thúc trong %1$s",
    "discount_desc_preset_weeklong_date": "ƯU ĐÃI XUYÊN TUẦN! Kết thúc vào %1$s",
    "discount_desc_preset_prepurchase": "KHUYẾN MÃI KHI ĐẶT MUA TRƯỚC! Kết thúc trong %1$s",
    "discount_desc_preset_prepurchase_date": "KHUYẾN MÃI KHI ĐẶT MUA TRƯỚC! Kết thúc vào %1$s",
    "discount_desc_preset_launch": "ƯU ĐÃI CHÀO HÀNG! Kết thúc trong %1$s",
    "discount_desc_preset_launch_date": "ƯU ĐÃI CHÀO HÀNG! Kết thúc vào %1$s",
    "discount_desc_preset_lunarnewyear": "ƯU ĐÃI TẾT ÂM LỊCH! Kết thúc trong %1$s",
    "discount_desc_preset_lunarnewyear_date": "ƯU ĐÃI TẾT ÂM LỊCH! Kết thúc vào %1$s",
    "discount_desc_indie_spring2013": "GIẢM GIÁ INDIE! Kết thúc trong %1$s"
}
