{
    "AppPage_PurchaseOptions_Title": "PURCHASE OPTIONS",
    "AppPage_BuyThisBundle": "Buy this bundle to save %2$s% off this remaining item!",
    "AppPage_BuyThisBundle_Plural": "Buy this bundle to save %2$s% off all %1$s items!",
    "AppPage_BuyThisBundle_Partial": "Buy this bundle to save %2$s% off the item you don't yet have!",
    "AppPage_BuyThisBundle_Partial_Plural": "Buy this bundle to save %2$s% off the %1$s items you don't yet have!",
    "AppPage_CollectionComplete": "Collection Complete! %1$s of %1$s items from this collection are already in your library.",
    "AppPage_CollectionComplete_Plural": "Collection Complete! %1$s of %1$s items from this collection are already in your library.",
    "AppPage_AdditionalItems": "And %1$s additional items",
    "AppPage_PurchaseOption_DownloadDemo": "Download %1$s",
    "AppPage_PurchaseOption_Bundle": "BUNDLE",
    "AppPage_PurchaseOption_InLibrary": "IN LIBRARY",
    "AppPage_PurchaseOption_CompleteYourCollection": "COMPLETE YOUR COLLECTION",
    "AppPage_PurchaseOption_InCart": "IN CART",
    "AppPage_PurchaseOption_Play": "Play %1$s",
    "AppPage_PurchaseOption_Play_Description": "%1$s is already in your Steam library",
    "AppPage_PurchaseOption_FreeToPlay": "Free To Play",
    "AppPage_PurchaseOption_FreeDemo": "Free Demo",
    "AppPage_PurchaseOption_FreeWeekend": "Play for free until %1$s",
    "AppPage_PurchaseOption_GetFreeToKeep": "Get %1$s",
    "AppPage_PurchaseOption_FreeToKeepDescription": "Free to keep when you get it before %1$s. Some limitations apply.",
    "AppPage_PurchaseOption_IncludedWithMasterSub": "Included with your <1>%1$s</1> subscription.",
    "AppPage_PurchaseOption_JoinPlaytest": "Join the %1$s",
    "AppPage_PurchaseOption_JoinPlaytest_Description": "Request access and you’ll get notified when the developer is ready for more participants.",
    "AppPage_PurchaseOption_JoinPlaytest_InvitePending": "You've requested access! Keep an eye out for an email notification from Steam when the developer is ready to accept more participants.",
    "AppPage_PurchaseOption_Playtest_Accepted_Title": "Play the %1$s now!",
    "AppPage_PurchaseOption_Playtest_Accepted": "You have been invited to play! Click to install and get started.",
    "AppPage_PurchaseOption_Playtest_Accepted_Unavailable_Title": "You are in the %1$s",
    "AppPage_PurchaseOption_Playtest_Accepted_Unavailable": "This Playtest is not currently active. Watch for upcoming testing plans from the developer.",
    "AppPage_PurchaseOption_Playtest_Open_Unreleased": "The Playtest will be added to your Steam Library when it's available. Watch for upcoming testing plans from the developer.",
    "AppPage_PurchaseOption_Playtest_Open": "The Playtest will be added to your Steam Library.",
    "AppPage_Prepurchase": "Pre-Purchase %1$s",
    "AppPage_Dropdown_DefaultTitle": "Buy %1$s",
    "AppPage_Dropdown_DefaultDescription_Subscription": "To be billed on a recurring basis.",
    "AppPage_PurchaseOption_JoinPlaytest_InvitedByFriend": "A friend has invited you to join the Playtest.",
    "AppPage_PurchaseOption_AddToCart": "ADD TO CART",
    "AppPage_PurchaseOption_PlayNow": "PLAY",
    "AppPage_PurchaseOption_MoreInfo": "INFO",
    "AppPage_PurchaseOption_BundleInfo": "BUNDLE INFO",
    "AppPage_PurchaseOption_CompareEditions": "COMPARE EDITIONS",
    "AppPage_PurchaseOption_AddToLibrary": "ADD TO LIBRARY",
    "AppPage_PurchaseOption_Download": "DOWNLOAD",
    "AppPage_PurchaseOption_ViewOptions": "VIEW PURCHASE OPTIONS",
    "AppPage_PurchaseOption_AddedToLibrary": "%1$s has been added to your account. It is now available in your Steam Library.",
    "AppPage_PurchaseOption_AddToLibraryError": "Could not add %1$s to your account. (%2$s)",
    "AppPage_SummaryBar_SteamDeckCompat": "STEAM DECK COMPATIBILITY",
    "AppPage_SummaryBar_SteamOSCompat": "STEAMOS COMPATIBILITY",
    "AppPage_SummaryBar_SteamMachineCompat": "STEAM MACHINE COMPATIBILITY",
    "AppPage_SummaryBar_UserTags": "USER TAGS",
    "AppPage_SummaryBar_UserReviews": "REVIEWS",
    "AppPage_SummaryBar_GameInfo": "GAME INFO",
    "AppPage_SummaryBar_Developer": "Developer",
    "AppPage_SummaryBar_Publisher": "Publisher",
    "AppPage_SummaryBar_ReleaseDate": "Released",
    "AppPage_SummaryBar_AndMore": ", and %1$s more.",
    "AppPage_Reviews_AllTime": "ALL TIME:",
    "AppPage_Reviews_Recent": "RECENT:",
    "AppPage_ReviewStats": "%1$s% of %2$s",
    "AppPage_Discount_Last30": "Discount based on lowest price in previous 30 days",
    "AppPage_AdvanceAccess_Banner": "ADVANCE ACCESS Starts %1$s",
    "AppPage_AdvanceAccess_Starts": "Pre-Purchase this edition and play the game starting %2$s ahead of full release. Starts in approximately %1$s.",
    "AppPage_AdvanceAccess_Now": "Purchase this edition and play the game now, ahead of full release.",
    "AppPage_AdvanceAccess_Starts_Owned": "You will be able to play this game %2$s ahead of full release via Advance Access. Starts in approximately %1$s.",
    "AppPage_AdvanceAccess_Now_Owned": "Play now! You can play this game via Advance Access ahead of full release.",
    "AppPage_DLCWarning_Title": "Downloadable Content",
    "AppPage_DLCWarning_Title_Soundtrack": "Downloadable Soundtrack",
    "AppPage_DLCWarning": "This content requires the base game %1$s on Steam in order to play.",
    "AppPage_DLCWarning_Software": "This content requires the base application %1$s on Steam in order to run.",
    "AppPage_DLCWarning_OneOf": "This content requires one of the following products to play:",
    "AppPage_DLCWarning_Soundtrack": "This is additional content for %1$s, but does not include the base game.",
    "AppPage_Features": "Features",
    "feature_profile_features_limited": "Profile Features Limited",
    "feature_learning_about_game": "Steam is learning about this game",
    "feature_learning_about_software": "Steam is learning about this software",
    "feature_learning_about_dlc": "Steam is learning about this downloadable content",
    "feature_learning_about_mod": "Steam is learning about this mod",
    "feature_learning_about_desc_game": "This game is not currently eligible to appear in certain showcases on your Steam Profile, and does not contribute to global Achievement or game collector counts.",
    "feature_learning_about_desc_software": "This product is not currently eligible to appear in certain showcases on your Steam Profile, and does not contribute to global Achievement or game collector counts.",
    "feature_learning_about_desc_dlc": "This downloadable content is not currently eligible to appear in certain showcases on your Steam Profile, and does not contribute to global Achievement or game collector counts.",
    "feature_learning_about_desc_mod": "This mod is not currently eligible to appear in certain showcases on your Steam Profile, and does not contribute to global Achievement or game collector counts.",
    "feature_third_party_drm": "Incorporates 3rd-party DRM: %1$s",
    "feature_third_party_eula": "Requires agreement to a 3rd-party EULA",
    "feature_third_party_eula_link": "View EULA",
    "feature_third_party_refund_playtime": "Steam refunds will consider EA account playtime",
    "feature_master_sub_app_eula": "%1$s subscription requires acceptance of a 3rd-party EULA",
    "feature_third_party_eula_accepted_date": "Accepted on %s",
    "feature_third_party_eula_rejected_date": "Rejected on %s",
    "feature_third_party_eula_accept": "Accept",
    "feature_third_party_eula_reject": "Reject",
    "feature_third_party_eula_login": "Please login to continue",
    "feature_external_account_service": "Requires 3rd-Party Account",
    "feature_external_account_service_canlink": " (Supports Linking to Steam Account)",
    "feature_package_may_contain_account_service": "One or more products in this package may require a 3rd party user account from %s.",
    "feature_includes_non_kernel_anti_cheat": "Uses Anti-Cheat Software",
    "feature_includes_kernel_anti_cheat": "Uses Kernel Level Anti-Cheat",
    "feature_anti_cheat_requires_manual_removal": " - Requires manual removal after game uninstall",
    "feature_package_may_contain_anticheat": "One or more products in this package may require anti-cheat software from %s.",
    "feature_anticheat_bootprotection": "Boot Protection",
    "feature_anticheat_bootprotection_secureboottpm2_desc": " - Requires both Secure Boot & TPM 2.0",
    "feature_bootprotectionbanner_secureboottpm2_header": "Secure Boot & TPM 2.0 Not Detected",
    "feature_bootprotectionbanner_secureboottpm2_desc": "Secure Boot and TPM 2.0 must be enabled to play some or all parts of this game. Steam has checked your system and one or both of these settings appear to be disabled. You can learn more about this game requirement on the <a %1$s>Steam Support Site</a>.",
    "feature_ai_generated_content_external_account_service": "Connects to 3rd-Party Service for AI Content Generation <1>%1$s</1>",
    "feature_package_may_contain_drm": "One or more products in this package may use the 3rd party DRM %s.",
    "feature_machine_activation_limit": "%1$s machine activation limit",
    "feature_machine_activation_limit_unlimited": "Unlimited machine activations",
    "languages_supported": "Languages Supported (%1$s)",
    "language_header_interface": "Interface",
    "language_header_interface_video": "Original",
    "language_header_full_audio": "Full Audio",
    "language_header_full_audio_short": "Audio",
    "language_header_subtitles": "Subtitles",
    "language_not_supported": "Not supported",
    "language_supported_interface": "%1$s interface",
    "language_supported_subtitles": "%1$s subtitles",
    "language_supported_subtitles_audio": "%1$s subtitles and audio",
    "language_supported_audio": "%1$s full audio",
    "language_not_supported_inline": "%1$s not supported",
    "music_disc_tab": "Disc %1$s",
    "music_localized_track_name": "%1$s (%2$s)",
    "music_album_track_duration": "%1$s:%2$s",
    "music_album_metadata": "Credits",
    "music_album_metadata_key_artist": "Artist:",
    "music_album_metadata_key_label": "Label:",
    "music_album_metadata_key_composer": "Composer:",
    "music_album_metadata_key_othercredits": "Other Credits:",
    "button_follow": "Follow",
    "button_follow_undo": "Followed",
    "button_ignore": "Ignore",
    "button_ignore_undo": "Ignored",
    "button_wishlist": "Add to your wishlist",
    "button_wishlist_undo": "On your Wishlist",
    "wishlist_manage_categories": "Manage Wishlist Categories",
    "ignore_reason_none_header": "Don't Ignore",
    "ignore_reason_none_desc": "",
    "ignore_reason_generic_header": "Ignore This",
    "ignore_reason_generic_desc": "Hide from store, ignore notifications, and don't use this to generate other recommendations.",
    "ignore_reason_otherstore_header": "Played on Another Platform",
    "ignore_reason_otherstore_desc": "Hide from store. Can be used to generate recommendations.",
    "discount_desc_mastersub": "Save %2$s% with %3$s when you purchase %4$s for your account",
    "discount_desc_preset_special": "SPECIAL PROMOTION! Offer ends in %1$s",
    "discount_desc_preset_special_date": "SPECIAL PROMOTION! Offer ends %1$s",
    "discount_desc_preset_weekend": "WEEKEND DEAL! Offer ends in %1$s",
    "discount_desc_preset_weekend_date": "WEEKEND DEAL! Offer ends %1$s",
    "discount_desc_preset_daily": "DAILY DEAL! Offer ends in %1$s",
    "discount_desc_preset_daily_date": "DAILY DEAL! Offer ends %1$s",
    "discount_desc_preset_midweek": "MIDWEEK DEAL! Offer ends in %1$s",
    "discount_desc_preset_midweek_date": "MIDWEEK DEAL! Offer ends %1$s",
    "discount_desc_limited_time": "Limited Time Offer",
    "discount_desc_limited_time_date": "Limited Time Offer",
    "discount_desc_preset_loyalty": "LOYALTY DISCOUNT! Offer ends in %1$s",
    "discount_desc_preset_loyalty_date": "LOYALTY DISCOUNT! Offer ends %1$s",
    "discount_desc_preset_promotion": "PROMOTIONAL PRICE! Offer ends in %1$s",
    "discount_desc_preset_promotion_date": "PROMOTIONAL PRICE! Offer ends %1$s",
    "discount_desc_preset_halloween": "HALLOWEEN SALE! Offer ends in %1$s",
    "discount_desc_preset_mystery_midweek": "MYSTERY MIDWEEK SALE! Offer ends in %1$s",
    "discount_desc_preset_cyberpunk_midweek": "CYBERPUNK MIDWEEK SALE! Offer ends in %1$s",
    "discount_desc_preset_halloween_date": "HALLOWEEN SALE! Offer ends %1$s",
    "discount_desc_preset_autumn": "AUTUMN SALE! Offer ends in %1$s",
    "discount_desc_preset_autumn_date": "AUTUMN SALE! Offer ends %1$s",
    "discount_desc_preset_holiday": "HOLIDAY SALE! Offer ends in %1$s",
    "discount_desc_preset_holiday_date": "HOLIDAY SALE! Offer ends %1$s",
    "discount_desc_preset_summer": "SUMMER SALE! Offer ends in %1$s",
    "discount_desc_preset_summer_date": "SUMMER SALE! Offer ends %1$s",
    "discount_desc_preset_flash_6": "FLASH SALE! Offer ends in %1$s",
    "discount_desc_preset_flash_6_date": "FLASH SALE! Offer ends %1$s",
    "discount_desc_preset_flash_8": "FLASH SALE! Offer ends in %1$s",
    "discount_desc_preset_flash_8_date": "FLASH SALE! Offer ends %1$s",
    "discount_desc_preset_flash_10": "FLASH SALE! Offer ends in %1$s",
    "discount_desc_preset_flash_10_date": "FLASH SALE! Offer ends %1$s",
    "discount_desc_preset_flash_12": "FLASH SALE! Offer ends in %1$s",
    "discount_desc_preset_flash_12_date": "FLASH SALE! Offer ends %1$s",
    "discount_desc_preset_vote": "SPECIAL PROMOTION! Offer ends in %1$s",
    "discount_desc_preset_vote_date": "SPECIAL PROMOTION! Offer ends %1$s",
    "discount_desc_preset_publisher": "PUBLISHER PACK! Offer ends in %1$s",
    "discount_desc_preset_publisher_date": "PUBLISHER PACK! Offer ends %1$s",
    "discount_desc_preset_weeklong": "WEEK LONG DEAL! Offer ends in %1$s",
    "discount_desc_preset_weeklong_date": "WEEK LONG DEAL! Offer ends %1$s",
    "discount_desc_preset_prepurchase": "PRE-PURCHASE PROMOTION! Offer ends in %1$s",
    "discount_desc_preset_prepurchase_date": "PRE-PURCHASE PROMOTION! Offer ends %1$s",
    "discount_desc_preset_launch": "INTRODUCTORY OFFER! Offer ends in %1$s",
    "discount_desc_preset_launch_date": "INTRODUCTORY OFFER! Offer ends %1$s",
    "discount_desc_preset_lunarnewyear": "LUNAR NEW YEAR SALE! Offer ends in %1$s",
    "discount_desc_preset_lunarnewyear_date": "LUNAR NEW YEAR SALE! Offer ends %1$s",
    "discount_desc_indie_spring2013": "INDIE SALE! Offer ends in %1$s",
    "category_mods": "Mods (require HL2)",
    "category_community_mod": "Community-Made Mod",
    "category_community_mod_description": "Click <a href=\"%s\" target=\"_blank\">here</a> to learn more about mods on Steam.",
    "category_hl1mods": "Mods (require HL1)",
    "category_most_players": "Most players",
    "category_multiplayer": "Multi-player",
    "category_multiplay_games": "Multi-player Games",
    "category_new_releases": "New Releases",
    "category_popular_new_releases": "Popular New Releases",
    "category_prerelease": "Pre-release",
    "category_singleplayer": "Single-player",
    "category_singleplay_games": "Single-player Games",
    "category_vac_enabled": "Valve Anti-Cheat enabled",
    "category_demo": "Game demo",
    "category_friends": "Friends enabled",
    "category_hdr": "HDR available",
    "category_cc": "Captions available",
    "category_commentary": "Commentary available",
    "category_mod_hl1": "Half-Life Mod",
    "category_mod_hl2": "Half-Life 2 Mod",
    "category_sdk": "Includes Source SDK",
    "category_editor": "Includes level editor",
    "category_controller": "Partial Controller Support",
    "category_controller_full": "Full controller support",
    "category_steam_controller": "Played with Steam Controller",
    "category_stats": "Stats",
    "category_mmo": "MMO",
    "category_DLC": "Downloadable Content",
    "category_soundtrack_DLCRegionHeader": "Downloadable Soundtrack",
    "category_soundtrack": "Soundtracks",
    "category_playtests": "Playtests",
    "category_steam_achievements": "Steam Achievements",
    "category_steam_cloud": "Steam Cloud",
    "category_pvp": "PvP",
    "category_highqualityaudio": "Additional High-Quality Audio",
    "category_online_pvp": "Online PvP",
    "category_lan_pvp": "LAN PvP",
    "category_local_pvp": "Shared/Split Screen PvP",
    "category_coop": "Co-op",
    "category_online_coop": "Online Co-op",
    "category_lan_coop": "LAN Co-op",
    "category_local_coop": "Shared/Split Screen Co-op",
    "category_shared_splitscreen": "Shared/Split Screen",
    "category_steam_leaderboards": "Steam Leaderboards",
    "category_coop_games": "Co-op Games",
    "category_cross_platform_multi": "Cross-Platform Multiplayer",
    "category_new_releases_filter_dlc": "Show downloadable content",
    "category_steam_trading_cards": "Steam Trading Cards",
    "category_steamvr_collectibles": "SteamVR Collectibles",
    "category_steam_workshop": "Steam Workshop",
    "category_timeline": "Steam Timeline",
    "category_vr": "VR Support",
    "category_vr_limited": "VR Support",
    "category_vr_steam": "Steam VR Support",
    "category_game_notifications": "Steam Turn Notifications",
    "category_video": "Streaming Video",
    "category_in-app_purchases": "In-App Purchases",
    "category_remoteplay_phone": "Remote Play on Phone",
    "category_remoteplay_tablet": "Remote Play on Tablet",
    "category_remoteplay_tv": "Remote Play on TV",
    "category_remoteplay_together": "Remote Play Together",
    "category_trackedmotioncontroller": "Tracked Controller Support",
    "category_vrsupported": "VR Supported",
    "category_vronly": "VR Only",
    "category_ps4": "DualShock Controller Support",
    "category_ps4bt": "DualShock Controller Support",
    "category_ps5": "DualSense Controller Support",
    "category_ps5bt": "DualSense Controller Support",
    "category_siapi": "Steam Input API Support",
    "category_gamepadonly": "Gamepad Only",
    "category_gamepadrecommended": "Gamepad Recommended",
    "category_family_sharing": "Family Sharing"
}
